{
"meta":{"test_sets":[],"test_metrics":[],"learn_metrics":[{"best_value":"Min","name":"RMSE"}],"launch_mode":"Train","parameters":"","iteration_count":1000,"learn_sets":["learn"],"name":"experiment"},
"iterations":[
{"learn":[14.61268541],"iteration":0,"passed_time":0.1473967484,"remaining_time":147.2493516},
{"learn":[14.23196558],"iteration":1,"passed_time":0.1482052408,"remaining_time":73.95441516},
{"learn":[13.86674177],"iteration":2,"passed_time":0.148834694,"remaining_time":49.46272996},
{"learn":[13.49946468],"iteration":3,"passed_time":0.1494907602,"remaining_time":37.22319929},
{"learn":[13.16661202],"iteration":4,"passed_time":0.1500600627,"remaining_time":29.86195247},
{"learn":[12.85632158],"iteration":5,"passed_time":0.1506169402,"remaining_time":24.95220642},
{"learn":[12.56784336],"iteration":6,"passed_time":0.1511650902,"remaining_time":21.44384779},
{"learn":[12.31617801],"iteration":7,"passed_time":0.151741066,"remaining_time":18.81589219},
{"learn":[12.01509946],"iteration":8,"passed_time":0.152294667,"remaining_time":16.76933499},
{"learn":[11.71512571],"iteration":9,"passed_time":0.152826905,"remaining_time":15.1298636},
{"learn":[11.43264457],"iteration":10,"passed_time":0.1534085923,"remaining_time":13.79282707},
{"learn":[11.17973129],"iteration":11,"passed_time":0.153953105,"remaining_time":12.67547231},
{"learn":[10.93746433],"iteration":12,"passed_time":0.1546937714,"remaining_time":11.7448271},
{"learn":[10.69387075],"iteration":13,"passed_time":0.1552665608,"remaining_time":10.93520207},
{"learn":[10.4615922],"iteration":14,"passed_time":0.1558589696,"remaining_time":10.234739},
{"learn":[10.2299235],"iteration":15,"passed_time":0.1564799558,"remaining_time":9.623517281},
{"learn":[10.01419731],"iteration":16,"passed_time":0.1571230062,"remaining_time":9.085406772},
{"learn":[9.795856918],"iteration":17,"passed_time":0.1577977005,"remaining_time":8.608741214},
{"learn":[9.60040151],"iteration":18,"passed_time":0.1583859206,"remaining_time":8.177715162},
{"learn":[9.418664989],"iteration":19,"passed_time":0.1590366267,"remaining_time":7.792794707},
{"learn":[9.249278645],"iteration":20,"passed_time":0.1596978736,"remaining_time":7.444962776},
{"learn":[9.090113396],"iteration":21,"passed_time":0.1603433641,"remaining_time":7.127991369},
{"learn":[8.909548708],"iteration":22,"passed_time":0.1609735387,"remaining_time":6.837875971},
{"learn":[8.740140208],"iteration":23,"passed_time":0.1616229273,"remaining_time":6.572665712},
{"learn":[8.59377682],"iteration":24,"passed_time":0.1623422906,"remaining_time":6.331349334},
{"learn":[8.453885414],"iteration":25,"passed_time":0.1629957322,"remaining_time":6.106070892},
{"learn":[8.317732234],"iteration":26,"passed_time":0.1636196643,"remaining_time":5.896367902},
{"learn":[8.180896085],"iteration":27,"passed_time":0.1642858111,"remaining_time":5.703064585},
{"learn":[8.053220863],"iteration":28,"passed_time":0.1649107449,"remaining_time":5.521666664},
{"learn":[7.924234474],"iteration":29,"passed_time":0.1655458797,"remaining_time":5.352650111},
{"learn":[7.818879511],"iteration":30,"passed_time":0.1661792705,"remaining_time":5.194442358},
{"learn":[7.719346395],"iteration":31,"passed_time":0.1667597356,"remaining_time":5.044482003},
{"learn":[7.624163594],"iteration":32,"passed_time":0.167354048,"remaining_time":4.903980739},
{"learn":[7.524952543],"iteration":33,"passed_time":0.1679538018,"remaining_time":4.771863899},
{"learn":[7.424464745],"iteration":34,"passed_time":0.1690006626,"remaining_time":4.659589698},
{"learn":[7.327482321],"iteration":35,"passed_time":0.1697504573,"remaining_time":4.545540022},
{"learn":[7.238666841],"iteration":36,"passed_time":0.1704043595,"remaining_time":4.43511887},
{"learn":[7.158842395],"iteration":37,"passed_time":0.1712051064,"remaining_time":4.33419243},
{"learn":[7.074348246],"iteration":38,"passed_time":0.1718828413,"remaining_time":4.235369499},
{"learn":[6.992269093],"iteration":39,"passed_time":0.1724627149,"remaining_time":4.139105158},
{"learn":[6.925219745],"iteration":40,"passed_time":0.1730590717,"remaining_time":4.047893896},
{"learn":[6.86013671],"iteration":41,"passed_time":0.1736446067,"remaining_time":3.960750791},
{"learn":[6.786739622],"iteration":42,"passed_time":0.174256715,"remaining_time":3.87822503},
{"learn":[6.73057926],"iteration":43,"passed_time":0.1748581775,"remaining_time":3.799191311},
{"learn":[6.666356486],"iteration":44,"passed_time":0.1754616585,"remaining_time":3.723686309},
{"learn":[6.606182832],"iteration":45,"passed_time":0.1765637951,"remaining_time":3.661779576},
{"learn":[6.547854615],"iteration":46,"passed_time":0.1771571358,"remaining_time":3.592143625},
{"learn":[6.49240675],"iteration":47,"passed_time":0.1778041994,"remaining_time":3.526449955},
{"learn":[6.431317261],"iteration":48,"passed_time":0.1785913287,"remaining_time":3.466129665},
{"learn":[6.377586395],"iteration":49,"passed_time":0.1793075757,"remaining_time":3.406843938},
{"learn":[6.327558015],"iteration":50,"passed_time":0.1800341841,"remaining_time":3.350047858},
{"learn":[6.282040317],"iteration":51,"passed_time":0.1807068236,"remaining_time":3.2944244},
{"learn":[6.237655841],"iteration":52,"passed_time":0.1813878703,"remaining_time":3.241024778},
{"learn":[6.192792003],"iteration":53,"passed_time":0.1821450598,"remaining_time":3.190911604},
{"learn":[6.150579347],"iteration":54,"passed_time":0.1828261266,"remaining_time":3.141285265},
{"learn":[6.115693845],"iteration":55,"passed_time":0.1835543783,"remaining_time":3.094202377},
{"learn":[6.078780782],"iteration":56,"passed_time":0.1841531896,"remaining_time":3.046604523},
{"learn":[6.045146957],"iteration":57,"passed_time":0.1847729512,"remaining_time":3.000967587},
{"learn":[6.008080327],"iteration":58,"passed_time":0.1854230054,"remaining_time":2.957339798},
{"learn":[5.977575734],"iteration":59,"passed_time":0.18614273,"remaining_time":2.916236104},
{"learn":[5.948036502],"iteration":60,"passed_time":0.1868020631,"remaining_time":2.875526841},
{"learn":[5.914888282],"iteration":61,"passed_time":0.1873790331,"remaining_time":2.834863436},
{"learn":[5.884957796],"iteration":62,"passed_time":0.1881710194,"remaining_time":2.798670558},
{"learn":[5.849539885],"iteration":63,"passed_time":0.188871929,"remaining_time":2.762251961},
{"learn":[5.821387627],"iteration":64,"passed_time":0.1895294463,"remaining_time":2.726308189},
{"learn":[5.797012279],"iteration":65,"passed_time":0.1901631,"remaining_time":2.691095991},
{"learn":[5.768685095],"iteration":66,"passed_time":0.1909213295,"remaining_time":2.658650752},
{"learn":[5.755484587],"iteration":67,"passed_time":0.1912742173,"remaining_time":2.62158192},
{"learn":[5.731887055],"iteration":68,"passed_time":0.1918819773,"remaining_time":2.589016244},
{"learn":[5.707148487],"iteration":69,"passed_time":0.1925006892,"remaining_time":2.557509156},
{"learn":[5.685365039],"iteration":70,"passed_time":0.1932192508,"remaining_time":2.528178648},
{"learn":[5.663541834],"iteration":71,"passed_time":0.1939241457,"remaining_time":2.499466767},
{"learn":[5.638108797],"iteration":72,"passed_time":0.1945527368,"remaining_time":2.470553247},
{"learn":[5.619204893],"iteration":73,"passed_time":0.1951334546,"remaining_time":2.441805121},
{"learn":[5.598472793],"iteration":74,"passed_time":0.1960322258,"remaining_time":2.417730784},
{"learn":[5.577007075],"iteration":75,"passed_time":0.1965960973,"remaining_time":2.390194657},
{"learn":[5.562637084],"iteration":76,"passed_time":0.1972994612,"remaining_time":2.365031204},
{"learn":[5.54729991],"iteration":77,"passed_time":0.1978867197,"remaining_time":2.339122507},
{"learn":[5.530737623],"iteration":78,"passed_time":0.1985488083,"remaining_time":2.314727247},
{"learn":[5.513704873],"iteration":79,"passed_time":0.1991747945,"remaining_time":2.290510137},
{"learn":[5.501575529],"iteration":80,"passed_time":0.1997613437,"remaining_time":2.266428085},
{"learn":[5.484080734],"iteration":81,"passed_time":0.2004216567,"remaining_time":2.243744888},
{"learn":[5.472178894],"iteration":82,"passed_time":0.2011113805,"remaining_time":2.2219173},
{"learn":[5.458923342],"iteration":83,"passed_time":0.2016646432,"remaining_time":2.199104918},
{"learn":[5.451382371],"iteration":84,"passed_time":0.2020954674,"remaining_time":2.175498267},
{"learn":[5.441410748],"iteration":85,"passed_time":0.2027493019,"remaining_time":2.15480072},
{"learn":[5.434047468],"iteration":86,"passed_time":0.2032320082,"remaining_time":2.132768086},
{"learn":[5.422107497],"iteration":87,"passed_time":0.2038841268,"remaining_time":2.112980951},
{"learn":[5.40731265],"iteration":88,"passed_time":0.204529412,"remaining_time":2.093553869},
{"learn":[5.396360181],"iteration":89,"passed_time":0.2051096962,"remaining_time":2.073886928},
{"learn":[5.383793239],"iteration":90,"passed_time":0.2058634989,"remaining_time":2.056372753},
{"learn":[5.369605034],"iteration":91,"passed_time":0.2064849363,"remaining_time":2.037916545},
{"learn":[5.357467333],"iteration":92,"passed_time":0.20710469,"remaining_time":2.01982746},
{"learn":[5.341109968],"iteration":93,"passed_time":0.207694233,"remaining_time":2.001818884},
{"learn":[5.330529276],"iteration":94,"passed_time":0.2083869532,"remaining_time":1.985159922},
{"learn":[5.319862075],"iteration":95,"passed_time":0.2090468696,"remaining_time":1.968524688},
{"learn":[5.313052243],"iteration":96,"passed_time":0.2096748397,"remaining_time":1.951921446},
{"learn":[5.299677207],"iteration":97,"passed_time":0.2107878833,"remaining_time":1.940108885},
{"learn":[5.287546698],"iteration":98,"passed_time":0.2115028681,"remaining_time":1.924889739},
{"learn":[5.279803754],"iteration":99,"passed_time":0.2121451015,"remaining_time":1.909305913},
{"learn":[5.272254612],"iteration":100,"passed_time":0.2128131976,"remaining_time":1.894248165},
{"learn":[5.268813888],"iteration":101,"passed_time":0.213258892,"remaining_time":1.877514559},
{"learn":[5.258113767],"iteration":102,"passed_time":0.2139049185,"remaining_time":1.862841863},
{"learn":[5.251018576],"iteration":103,"passed_time":0.2145056886,"remaining_time":1.848049009},
{"learn":[5.24171237],"iteration":104,"passed_time":0.2150322954,"remaining_time":1.832894327},
{"learn":[5.233984943],"iteration":105,"passed_time":0.2156414633,"remaining_time":1.818711964},
{"learn":[5.226240449],"iteration":106,"passed_time":0.2163388928,"remaining_time":1.805519919},
{"learn":[5.220541644],"iteration":107,"passed_time":0.2170002946,"remaining_time":1.792261693},
{"learn":[5.211712096],"iteration":108,"passed_time":0.2176272883,"remaining_time":1.778953338},
{"learn":[5.203388597],"iteration":109,"passed_time":0.2182687201,"remaining_time":1.765992371},
{"learn":[5.196026544],"iteration":110,"passed_time":0.2189035516,"remaining_time":1.753200517},
{"learn":[5.188716772],"iteration":111,"passed_time":0.2195147156,"remaining_time":1.740438102},
{"learn":[5.182163132],"iteration":112,"passed_time":0.2200734368,"remaining_time":1.727479101},
{"learn":[5.17764747],"iteration":113,"passed_time":0.220678471,"remaining_time":1.71509759},
{"learn":[5.170548056],"iteration":114,"passed_time":0.2213149804,"remaining_time":1.70316311},
{"learn":[5.165901827],"iteration":115,"passed_time":0.221876517,"remaining_time":1.690852078},
{"learn":[5.160333668],"iteration":116,"passed_time":0.222642226,"remaining_time":1.680282782},
{"learn":[5.148953243],"iteration":117,"passed_time":0.2234315876,"remaining_time":1.670056443},
{"learn":[5.144729126],"iteration":118,"passed_time":0.223992714,"remaining_time":1.658299},
{"learn":[5.139939946],"iteration":119,"passed_time":0.2245888803,"remaining_time":1.646985122},
{"learn":[5.132898872],"iteration":120,"passed_time":0.2252353476,"remaining_time":1.636213806},
{"learn":[5.129073077],"iteration":121,"passed_time":0.2259582182,"remaining_time":1.626158325},
{"learn":[5.127123916],"iteration":122,"passed_time":0.2263058859,"remaining_time":1.613579365},
{"learn":[5.121282057],"iteration":123,"passed_time":0.2269168617,"remaining_time":1.603057829},
{"learn":[5.114489821],"iteration":124,"passed_time":0.2275492532,"remaining_time":1.592844772},
{"learn":[5.107777291],"iteration":125,"passed_time":0.2283550329,"remaining_time":1.583986498},
{"learn":[5.103518754],"iteration":126,"passed_time":0.2290076926,"remaining_time":1.574202485},
{"learn":[5.101133351],"iteration":127,"passed_time":0.2294517987,"remaining_time":1.563140378},
{"learn":[5.096462705],"iteration":128,"passed_time":0.2301109617,"remaining_time":1.553694943},
{"learn":[5.08562082],"iteration":129,"passed_time":0.230768521,"remaining_time":1.544373948},
{"learn":[5.080483682],"iteration":130,"passed_time":0.2314310208,"remaining_time":1.535217993},
{"learn":[5.07437499],"iteration":131,"passed_time":0.2320809247,"remaining_time":1.526107899},
{"learn":[5.070683732],"iteration":132,"passed_time":0.2327449475,"remaining_time":1.517217064},
{"learn":[5.06432037],"iteration":133,"passed_time":0.2334059139,"remaining_time":1.508429264},
{"learn":[5.057436484],"iteration":134,"passed_time":0.2340803774,"remaining_time":1.499848344},
{"learn":[5.053254656],"iteration":135,"passed_time":0.2346621196,"remaining_time":1.490794642},
{"learn":[5.04801663],"iteration":136,"passed_time":0.2352872192,"remaining_time":1.482137738},
{"learn":[5.045680836],"iteration":137,"passed_time":0.2357893717,"remaining_time":1.472829264},
{"learn":[5.041857933],"iteration":138,"passed_time":0.2365001581,"remaining_time":1.464939828},
{"learn":[5.035264888],"iteration":139,"passed_time":0.2370821961,"remaining_time":1.456362062},
{"learn":[5.028771948],"iteration":140,"passed_time":0.2376918195,"remaining_time":1.448065765},
{"learn":[5.024912247],"iteration":141,"passed_time":0.2382363923,"remaining_time":1.43948468},
{"learn":[5.02239068],"iteration":142,"passed_time":0.2388818776,"remaining_time":1.431620763},
{"learn":[5.017110572],"iteration":143,"passed_time":0.2395678697,"remaining_time":1.424097892},
{"learn":[5.010707886],"iteration":144,"passed_time":0.2401709897,"remaining_time":1.416180663},
{"learn":[5.004389868],"iteration":145,"passed_time":0.2408048417,"remaining_time":1.408543389},
{"learn":[4.997628683],"iteration":146,"passed_time":0.2414622613,"remaining_time":1.401138155},
{"learn":[4.991497851],"iteration":147,"passed_time":0.2420415034,"remaining_time":1.39337406},
{"learn":[4.988345253],"iteration":148,"passed_time":0.2426599147,"remaining_time":1.385930117},
{"learn":[4.98460423],"iteration":149,"passed_time":0.2434218737,"remaining_time":1.379390618},
{"learn":[4.982441783],"iteration":150,"passed_time":0.2441046338,"remaining_time":1.372482345},
{"learn":[4.977461771],"iteration":151,"passed_time":0.2447098684,"remaining_time":1.365223476},
{"learn":[4.973601586],"iteration":152,"passed_time":0.2452808864,"remaining_time":1.357862162},
{"learn":[4.968328804],"iteration":153,"passed_time":0.2459721916,"remaining_time":1.351249832},
{"learn":[4.9640736],"iteration":154,"passed_time":0.2466343801,"remaining_time":1.344555169},
{"learn":[4.960865882],"iteration":155,"passed_time":0.2472142638,"remaining_time":1.337492555},
{"learn":[4.957014156],"iteration":156,"passed_time":0.2477673039,"remaining_time":1.33036839},
{"learn":[4.952244852],"iteration":157,"passed_time":0.2484288235,"remaining_time":1.323905503},
{"learn":[4.949695675],"iteration":158,"passed_time":0.249166203,"remaining_time":1.317916835},
{"learn":[4.946584698],"iteration":159,"passed_time":0.249754005,"remaining_time":1.311208526},
{"learn":[4.940192834],"iteration":160,"passed_time":0.2504115921,"remaining_time":1.304939912},
{"learn":[4.936727994],"iteration":161,"passed_time":0.251147379,"remaining_time":1.299145084},
{"learn":[4.932342063],"iteration":162,"passed_time":0.2520375851,"remaining_time":1.294205268},
{"learn":[4.925830838],"iteration":163,"passed_time":0.2526819886,"remaining_time":1.288061844},
{"learn":[4.922571773],"iteration":164,"passed_time":0.253299127,"remaining_time":1.281847097},
{"learn":[4.918395814],"iteration":165,"passed_time":0.2539677888,"remaining_time":1.27595865},
{"learn":[4.911142452],"iteration":166,"passed_time":0.2546201304,"remaining_time":1.270051309},
{"learn":[4.908276131],"iteration":167,"passed_time":0.255346205,"remaining_time":1.264571682},
{"learn":[4.904584645],"iteration":168,"passed_time":0.2559518006,"remaining_time":1.258555895},
{"learn":[4.89795517],"iteration":169,"passed_time":0.256667757,"remaining_time":1.253142578},
{"learn":[4.895556491],"iteration":170,"passed_time":0.2572894248,"remaining_time":1.247327095},
{"learn":[4.890591233],"iteration":171,"passed_time":0.257872685,"remaining_time":1.241387111},
{"learn":[4.884629277],"iteration":172,"passed_time":0.2585461264,"remaining_time":1.235940153},
{"learn":[4.880550786],"iteration":173,"passed_time":0.2591903717,"remaining_time":1.230409466},
{"learn":[4.876384842],"iteration":174,"passed_time":0.2598005841,"remaining_time":1.224774182},
{"learn":[4.872638238],"iteration":175,"passed_time":0.2604677751,"remaining_time":1.219462765},
{"learn":[4.869137118],"iteration":176,"passed_time":0.2611990405,"remaining_time":1.214501753},
{"learn":[4.863587157],"iteration":177,"passed_time":0.2618010686,"remaining_time":1.208991452},
{"learn":[4.858028614],"iteration":178,"passed_time":0.2624814336,"remaining_time":1.20389529},
{"learn":[4.853838176],"iteration":179,"passed_time":0.2630503055,"remaining_time":1.198340281},
{"learn":[4.853462329],"iteration":180,"passed_time":0.2634146114,"remaining_time":1.191914733},
{"learn":[4.851573196],"iteration":181,"passed_time":0.2640704773,"remaining_time":1.186866211},
{"learn":[4.848442087],"iteration":182,"passed_time":0.2646366789,"remaining_time":1.181465392},
{"learn":[4.845547104],"iteration":183,"passed_time":0.2653744592,"remaining_time":1.176878036},
{"learn":[4.839868817],"iteration":184,"passed_time":0.2660418588,"remaining_time":1.172022243},
{"learn":[4.836336958],"iteration":185,"passed_time":0.266776132,"remaining_time":1.167504147},
{"learn":[4.831124789],"iteration":186,"passed_time":0.2673348432,"remaining_time":1.162263249},
{"learn":[4.827407333],"iteration":187,"passed_time":0.267941581,"remaining_time":1.157279595},
{"learn":[4.824088918],"iteration":188,"passed_time":0.26854916,"remaining_time":1.152345866},
{"learn":[4.820934539],"iteration":189,"passed_time":0.2692683132,"remaining_time":1.147933335},
{"learn":[4.816975227],"iteration":190,"passed_time":0.2698842091,"remaining_time":1.143122121},
{"learn":[4.812340486],"iteration":191,"passed_time":0.27048658,"remaining_time":1.138297691},
{"learn":[4.806402747],"iteration":192,"passed_time":0.2712477454,"remaining_time":1.134180987},
{"learn":[4.801521788],"iteration":193,"passed_time":0.2719555178,"remaining_time":1.129877048},
{"learn":[4.797601172],"iteration":194,"passed_time":0.2726141875,"remaining_time":1.125407287},
{"learn":[4.792694629],"iteration":195,"passed_time":0.2731599427,"remaining_time":1.120513234},
{"learn":[4.789794613],"iteration":196,"passed_time":0.2738861196,"remaining_time":1.116398752},
{"learn":[4.785367055],"iteration":197,"passed_time":0.2745093306,"remaining_time":1.11190143},
{"learn":[4.780376856],"iteration":198,"passed_time":0.2751555194,"remaining_time":1.107535533},
{"learn":[4.776691261],"iteration":199,"passed_time":0.2757174471,"remaining_time":1.102869788},
{"learn":[4.773470753],"iteration":200,"passed_time":0.2764719488,"remaining_time":1.099010383},
{"learn":[4.77207327],"iteration":201,"passed_time":0.27710542,"remaining_time":1.09470359},
{"learn":[4.767347177],"iteration":202,"passed_time":0.2779035717,"remaining_time":1.09107954},
{"learn":[4.763983068],"iteration":203,"passed_time":0.2786001395,"remaining_time":1.087086819},
{"learn":[4.761588849],"iteration":204,"passed_time":0.2792950543,"remaining_time":1.083119845},
{"learn":[4.758558086],"iteration":205,"passed_time":0.279911291,"remaining_time":1.078881384},
{"learn":[4.753678804],"iteration":206,"passed_time":0.2806219173,"remaining_time":1.075039519},
{"learn":[4.746510889],"iteration":207,"passed_time":0.2813260801,"remaining_time":1.071203151},
{"learn":[4.744840601],"iteration":208,"passed_time":0.2819405034,"remaining_time":1.06705712},
{"learn":[4.741702222],"iteration":209,"passed_time":0.2825277415,"remaining_time":1.062842456},
{"learn":[4.739352853],"iteration":210,"passed_time":0.283106864,"remaining_time":1.058631828},
{"learn":[4.735539287],"iteration":211,"passed_time":0.2838948899,"remaining_time":1.055231949},
{"learn":[4.730726751],"iteration":212,"passed_time":0.2845635517,"remaining_time":1.051415564},
{"learn":[4.726416092],"iteration":213,"passed_time":0.2852901097,"remaining_time":1.047841244},
{"learn":[4.721293082],"iteration":214,"passed_time":0.2858498226,"remaining_time":1.043684236},
{"learn":[4.718443695],"iteration":215,"passed_time":0.2864964606,"remaining_time":1.039876042},
{"learn":[4.711627962],"iteration":216,"passed_time":0.2872763456,"remaining_time":1.036577782},
{"learn":[4.709790764],"iteration":217,"passed_time":0.2878969762,"remaining_time":1.032731355},
{"learn":[4.706913073],"iteration":218,"passed_time":0.2884510627,"remaining_time":1.028677077},
{"learn":[4.703846389],"iteration":219,"passed_time":0.2891736928,"remaining_time":1.025252184},
{"learn":[4.701001135],"iteration":220,"passed_time":0.2897759116,"remaining_time":1.021427308},
{"learn":[4.700380864],"iteration":221,"passed_time":0.2903467869,"remaining_time":1.017521623},
{"learn":[4.695837486],"iteration":222,"passed_time":0.2909105182,"remaining_time":1.013620954},
{"learn":[4.691242996],"iteration":223,"passed_time":0.2915405829,"remaining_time":1.009979876},
{"learn":[4.690284609],"iteration":224,"passed_time":0.2922121102,"remaining_time":1.006508379},
{"learn":[4.68827119],"iteration":225,"passed_time":0.2928140736,"remaining_time":1.00282342},
{"learn":[4.686922425],"iteration":226,"passed_time":0.2934176497,"remaining_time":0.9991711154},
{"learn":[4.686085874],"iteration":227,"passed_time":0.2941461367,"remaining_time":0.995968498},
{"learn":[4.683230741],"iteration":228,"passed_time":0.2948807858,"remaining_time":0.9928082353},
{"learn":[4.6773487],"iteration":229,"passed_time":0.2954369519,"remaining_time":0.9890715347},
{"learn":[4.671462906],"iteration":230,"passed_time":0.2959589494,"remaining_time":0.9852486239},
{"learn":[4.664799601],"iteration":231,"passed_time":0.2965703163,"remaining_time":0.9817500126},
{"learn":[4.660979386],"iteration":232,"passed_time":0.2971261918,"remaining_time":0.9780935155},
{"learn":[4.656281279],"iteration":233,"passed_time":0.2978029897,"remaining_time":0.9748593593},
{"learn":[4.651997094],"iteration":234,"passed_time":0.2984522225,"remaining_time":0.971557235},
{"learn":[4.650151977],"iteration":235,"passed_time":0.2990875177,"remaining_time":0.9682324725},
{"learn":[4.648478046],"iteration":236,"passed_time":0.2997299068,"remaining_time":0.9649532443},
{"learn":[4.646364602],"iteration":237,"passed_time":0.3003374961,"remaining_time":0.9615847564},
{"learn":[4.642635873],"iteration":238,"passed_time":0.3010226711,"remaining_time":0.9584864129},
{"learn":[4.640860821],"iteration":239,"passed_time":0.3016612425,"remaining_time":0.9552606013},
{"learn":[4.639446822],"iteration":240,"passed_time":0.3023325794,"remaining_time":0.9521594513},
{"learn":[4.637120072],"iteration":241,"passed_time":0.3029086955,"remaining_time":0.948780129},
{"learn":[4.633769267],"iteration":242,"passed_time":0.3035523071,"remaining_time":0.9456341419},
{"learn":[4.630491517],"iteration":243,"passed_time":0.3041864299,"remaining_time":0.9424792665},
{"learn":[4.627813333],"iteration":244,"passed_time":0.3047558927,"remaining_time":0.9391457102},
{"learn":[4.622496304],"iteration":245,"passed_time":0.3053851652,"remaining_time":0.9360179453},
{"learn":[4.618979301],"iteration":246,"passed_time":0.3060300393,"remaining_time":0.932957974},
{"learn":[4.616563458],"iteration":247,"passed_time":0.3066513063,"remaining_time":0.9298458966},
{"learn":[4.614759385],"iteration":248,"passed_time":0.3072769118,"remaining_time":0.9267669105},
{"learn":[4.61251363],"iteration":249,"passed_time":0.3080582497,"remaining_time":0.9241747491},
{"learn":[4.608796693],"iteration":250,"passed_time":0.3087555487,"remaining_time":0.921346239},
{"learn":[4.60847774],"iteration":251,"passed_time":0.309390318,"remaining_time":0.9183490391},
{"learn":[4.605195659],"iteration":252,"passed_time":0.3100321709,"remaining_time":0.9153914294},
{"learn":[4.60103766],"iteration":253,"passed_time":0.3106370544,"remaining_time":0.9123434748},
{"learn":[4.599325598],"iteration":254,"passed_time":0.3112115275,"remaining_time":0.9092258354},
{"learn":[4.597012808],"iteration":255,"passed_time":0.3118356552,"remaining_time":0.9062723728},
{"learn":[4.594161533],"iteration":256,"passed_time":0.3124938709,"remaining_time":0.9034355878},
{"learn":[4.592197259],"iteration":257,"passed_time":0.3131183237,"remaining_time":0.9005185899},
{"learn":[4.58952828],"iteration":258,"passed_time":0.3137470156,"remaining_time":0.8976314231},
{"learn":[4.585816572],"iteration":259,"passed_time":0.3143912135,"remaining_time":0.8948057616},
{"learn":[4.582934052],"iteration":260,"passed_time":0.3151393448,"remaining_time":0.8922910952},
{"learn":[4.582234842],"iteration":261,"passed_time":0.3158036425,"remaining_time":0.8895537715},
{"learn":[4.57571562],"iteration":262,"passed_time":0.3164993741,"remaining_time":0.8869202992},
{"learn":[4.571197349],"iteration":263,"passed_time":0.317104533,"remaining_time":0.8840490012},
{"learn":[4.56723703],"iteration":264,"passed_time":0.3176968219,"remaining_time":0.8811591098},
{"learn":[4.560335567],"iteration":265,"passed_time":0.3183100476,"remaining_time":0.8783442668},
{"learn":[4.554709345],"iteration":266,"passed_time":0.3189867702,"remaining_time":0.8757202343},
{"learn":[4.552806306],"iteration":267,"passed_time":0.3196914944,"remaining_time":0.8731872161},
{"learn":[4.550766241],"iteration":268,"passed_time":0.3203427717,"remaining_time":0.8705225505},
{"learn":[4.549216045],"iteration":269,"passed_time":0.3209237427,"remaining_time":0.8676827117},
{"learn":[4.547687452],"iteration":270,"passed_time":0.3215616777,"remaining_time":0.8650127788},
{"learn":[4.545642435],"iteration":271,"passed_time":0.3221835654,"remaining_time":0.8623148367},
{"learn":[4.543930359],"iteration":272,"passed_time":0.3228306193,"remaining_time":0.8596991217},
{"learn":[4.541029943],"iteration":273,"passed_time":0.3236341017,"remaining_time":0.8575122548},
{"learn":[4.537781449],"iteration":274,"passed_time":0.3243735355,"remaining_time":0.8551665937},
{"learn":[4.53066128],"iteration":275,"passed_time":0.3250676986,"remaining_time":0.852713818},
{"learn":[4.526763956],"iteration":276,"passed_time":0.3256807637,"remaining_time":0.8500620655},
{"learn":[4.522036004],"iteration":277,"passed_time":0.3263892305,"remaining_time":0.8476727498},
{"learn":[4.515307629],"iteration":278,"passed_time":0.3269931825,"remaining_time":0.8450253928},
{"learn":[4.51109143],"iteration":279,"passed_time":0.3276910074,"remaining_time":0.8426340191},
{"learn":[4.508233494],"iteration":280,"passed_time":0.328319424,"remaining_time":0.8400771026},
{"learn":[4.502555629],"iteration":281,"passed_time":0.3289154145,"remaining_time":0.8374513036},
{"learn":[4.500081355],"iteration":282,"passed_time":0.3295686958,"remaining_time":0.8349849996},
{"learn":[4.495281743],"iteration":283,"passed_time":0.3302308442,"remaining_time":0.8325538186},
{"learn":[4.492138869],"iteration":284,"passed_time":0.330880538,"remaining_time":0.8301038059},
{"learn":[4.491708261],"iteration":285,"passed_time":0.3314288984,"remaining_time":0.8274134038},
{"learn":[4.489398865],"iteration":286,"passed_time":0.3321107671,"remaining_time":0.825069606},
{"learn":[4.485796373],"iteration":287,"passed_time":0.3327659267,"remaining_time":0.8226713187},
{"learn":[4.479542205],"iteration":288,"passed_time":0.3333426036,"remaining_time":0.820092011},
{"learn":[4.475986993],"iteration":289,"passed_time":0.3340015414,"remaining_time":0.8177279117},
{"learn":[4.468661855],"iteration":290,"passed_time":0.3346474123,"remaining_time":0.8153436954},
{"learn":[4.463785664],"iteration":291,"passed_time":0.335307186,"remaining_time":0.8130050949},
{"learn":[4.460445831],"iteration":292,"passed_time":0.3360014693,"remaining_time":0.8107612245},
{"learn":[4.45692492],"iteration":293,"passed_time":0.3366012833,"remaining_time":0.8083010408},
{"learn":[4.454031688],"iteration":294,"passed_time":0.3375557887,"remaining_time":0.8067011222},
{"learn":[4.451672391],"iteration":295,"passed_time":0.3381804319,"remaining_time":0.8043210273},
{"learn":[4.45031553],"iteration":296,"passed_time":0.3387959875,"remaining_time":0.8019312431},
{"learn":[4.446782666],"iteration":297,"passed_time":0.3395241384,"remaining_time":0.7998186079},
{"learn":[4.444369689],"iteration":298,"passed_time":0.3400890921,"remaining_time":0.7973326207},
{"learn":[4.44411683],"iteration":299,"passed_time":0.3407309402,"remaining_time":0.7950388604},
{"learn":[4.440876943],"iteration":300,"passed_time":0.3413265754,"remaining_time":0.7926487583},
{"learn":[4.439336453],"iteration":301,"passed_time":0.3420585246,"remaining_time":0.7905855966},
{"learn":[4.436666901],"iteration":302,"passed_time":0.3426694903,"remaining_time":0.78825292},
{"learn":[4.433043336],"iteration":303,"passed_time":0.3433143447,"remaining_time":0.7860091576},
{"learn":[4.431419305],"iteration":304,"passed_time":0.3439255913,"remaining_time":0.7836992983},
{"learn":[4.428859646],"iteration":305,"passed_time":0.3445470384,"remaining_time":0.7814236754},
{"learn":[4.424552441],"iteration":306,"passed_time":0.3452578348,"remaining_time":0.7793605196},
{"learn":[4.422706391],"iteration":307,"passed_time":0.3458634401,"remaining_time":0.777069807},
{"learn":[4.421427994],"iteration":308,"passed_time":0.3464474918,"remaining_time":0.7747418021},
{"learn":[4.418733158],"iteration":309,"passed_time":0.3473031489,"remaining_time":0.7730295896},
{"learn":[4.415656941],"iteration":310,"passed_time":0.3479741057,"remaining_time":0.7709136939},
{"learn":[4.410747417],"iteration":311,"passed_time":0.3486362845,"remaining_time":0.7687877043},
{"learn":[4.408126521],"iteration":312,"passed_time":0.3492328316,"remaining_time":0.7665270138},
{"learn":[4.407843853],"iteration":313,"passed_time":0.3499047898,"remaining_time":0.7644416745},
{"learn":[4.405219398],"iteration":314,"passed_time":0.3506196847,"remaining_time":0.7624586794},
{"learn":[4.402708465],"iteration":315,"passed_time":0.3512388272,"remaining_time":0.7602764487},
{"learn":[4.40104971],"iteration":316,"passed_time":0.3519009258,"remaining_time":0.758196632},
{"learn":[4.400830038],"iteration":317,"passed_time":0.3524690459,"remaining_time":0.7559241802},
{"learn":[4.39784288],"iteration":318,"passed_time":0.3530742304,"remaining_time":0.7537415388},
{"learn":[4.393741845],"iteration":319,"passed_time":0.3537401667,"remaining_time":0.7516978543},
{"learn":[4.393425936],"iteration":320,"passed_time":0.3544184375,"remaining_time":0.7496888445},
{"learn":[4.390505974],"iteration":321,"passed_time":0.3550858472,"remaining_time":0.747665231},
{"learn":[4.390305136],"iteration":322,"passed_time":0.3557082164,"remaining_time":0.7455556115},
{"learn":[4.38568203],"iteration":323,"passed_time":0.3563706154,"remaining_time":0.7435386913},
{"learn":[4.383057135],"iteration":324,"passed_time":0.3570341068,"remaining_time":0.7415323757},
{"learn":[4.380662684],"iteration":325,"passed_time":0.3577747234,"remaining_time":0.7396937532},
{"learn":[4.37805727],"iteration":326,"passed_time":0.3583489457,"remaining_time":0.7375193897},
{"learn":[4.373708319],"iteration":327,"passed_time":0.3589927376,"remaining_time":0.7354973161},
{"learn":[4.36887921],"iteration":328,"passed_time":0.3596275916,"remaining_time":0.733465392},
{"learn":[4.367895929],"iteration":329,"passed_time":0.3602836278,"remaining_time":0.7314849413},
{"learn":[4.362140573],"iteration":330,"passed_time":0.3609180309,"remaining_time":0.7294687694},
{"learn":[4.361931924],"iteration":331,"passed_time":0.3614759107,"remaining_time":0.7273069529},
{"learn":[4.359656377],"iteration":332,"passed_time":0.3621421878,"remaining_time":0.7253718896},
{"learn":[4.354281355],"iteration":333,"passed_time":0.3628455092,"remaining_time":0.7235182907},
{"learn":[4.348589447],"iteration":334,"passed_time":0.3634607134,"remaining_time":0.7214966401},
{"learn":[4.346355698],"iteration":335,"passed_time":0.3640624309,"remaining_time":0.7194567087},
{"learn":[4.343894047],"iteration":336,"passed_time":0.3648807233,"remaining_time":0.7178513934},
{"learn":[4.341561356],"iteration":337,"passed_time":0.3656029426,"remaining_time":0.7160625681},
{"learn":[4.338869061],"iteration":338,"passed_time":0.3665179689,"remaining_time":0.7146559806},
{"learn":[4.333720063],"iteration":339,"passed_time":0.3674395631,"remaining_time":0.7132650343},
{"learn":[4.330892223],"iteration":340,"passed_time":0.3680649281,"remaining_time":0.7113043625},
{"learn":[4.328311474],"iteration":341,"passed_time":0.3688051059,"remaining_time":0.7095723966},
{"learn":[4.324580133],"iteration":342,"passed_time":0.3696942678,"remaining_time":0.7081315858},
{"learn":[4.323354432],"iteration":343,"passed_time":0.3704150345,"remaining_time":0.7063728564},
{"learn":[4.323159553],"iteration":344,"passed_time":0.3710014008,"remaining_time":0.7043649784},
{"learn":[4.318639682],"iteration":345,"passed_time":0.3715878179,"remaining_time":0.7023654131},
{"learn":[4.312712208],"iteration":346,"passed_time":0.3723703179,"remaining_time":0.7007429902},
{"learn":[4.311461062],"iteration":347,"passed_time":0.3730403224,"remaining_time":0.6989146271},
{"learn":[4.311178356],"iteration":348,"passed_time":0.3736113587,"remaining_time":0.6969082937},
{"learn":[4.311102505],"iteration":349,"passed_time":0.3741754127,"remaining_time":0.694897195},
{"learn":[4.310232308],"iteration":350,"passed_time":0.3749413276,"remaining_time":0.6932675829},
{"learn":[4.305128197],"iteration":351,"passed_time":0.3755575342,"remaining_time":0.6913672788},
{"learn":[4.304595496],"iteration":352,"passed_time":0.3763375695,"remaining_time":0.6897745254},
{"learn":[4.3004992],"iteration":353,"passed_time":0.3770070427,"remaining_time":0.6879846033},
{"learn":[4.297581524],"iteration":354,"passed_time":0.3776810756,"remaining_time":0.6862092782},
{"learn":[4.297355825],"iteration":355,"passed_time":0.3783221618,"remaining_time":0.6843805398},
{"learn":[4.295758715],"iteration":356,"passed_time":0.379287379,"remaining_time":0.6831422541},
{"learn":[4.292500657],"iteration":357,"passed_time":0.3801132263,"remaining_time":0.6816555622},
{"learn":[4.290797586],"iteration":358,"passed_time":0.3808450145,"remaining_time":0.6800046081},
{"learn":[4.286410608],"iteration":359,"passed_time":0.3814984157,"remaining_time":0.6782194057},
{"learn":[4.280278245],"iteration":360,"passed_time":0.3823511269,"remaining_time":0.6767932689},
{"learn":[4.279941283],"iteration":361,"passed_time":0.3830631157,"remaining_time":0.6751222868},
{"learn":[4.274426275],"iteration":362,"passed_time":0.38379781,"remaining_time":0.6734964325},
{"learn":[4.273567658],"iteration":363,"passed_time":0.3845791972,"remaining_time":0.6719570588},
{"learn":[4.269488271],"iteration":364,"passed_time":0.3853709266,"remaining_time":0.6704398312},
{"learn":[4.266838205],"iteration":365,"passed_time":0.386017454,"remaining_time":0.6686750433},
{"learn":[4.263456509],"iteration":366,"passed_time":0.3868044433,"remaining_time":0.6671586174},
{"learn":[4.260360204],"iteration":367,"passed_time":0.3877966669,"remaining_time":0.6659986235},
{"learn":[4.255120549],"iteration":368,"passed_time":0.3885197859,"remaining_time":0.6643793628},
{"learn":[4.252582211],"iteration":369,"passed_time":0.3892382877,"remaining_time":0.6627570845},
{"learn":[4.247857931],"iteration":370,"passed_time":0.3899297174,"remaining_time":0.6610937796},
{"learn":[4.245288911],"iteration":371,"passed_time":0.390620902,"remaining_time":0.6594352861},
{"learn":[4.24048515],"iteration":372,"passed_time":0.3914552563,"remaining_time":0.6580226426},
{"learn":[4.2378365],"iteration":373,"passed_time":0.3921430468,"remaining_time":0.6563677736},
{"learn":[4.236751063],"iteration":374,"passed_time":0.393014676,"remaining_time":0.65502446},
{"learn":[4.233240093],"iteration":375,"passed_time":0.3936916044,"remaining_time":0.653360535},
{"learn":[4.230358421],"iteration":376,"passed_time":0.3944379919,"remaining_time":0.6518166285},
{"learn":[4.225853583],"iteration":377,"passed_time":0.3953380381,"remaining_time":0.6505297875},
{"learn":[4.224702126],"iteration":378,"passed_time":0.3960919613,"remaining_time":0.6490055619},
{"learn":[4.224361982],"iteration":379,"passed_time":0.3968123469,"remaining_time":0.6474306713},
{"learn":[4.223787954],"iteration":380,"passed_time":0.3974565846,"remaining_time":0.6457365509},
{"learn":[4.22144054],"iteration":381,"passed_time":0.3981788392,"remaining_time":0.6441741429},
{"learn":[4.217739335],"iteration":382,"passed_time":0.3988632872,"remaining_time":0.6425552173},
{"learn":[4.215611665],"iteration":383,"passed_time":0.3995433222,"remaining_time":0.6409340793},
{"learn":[4.210236863],"iteration":384,"passed_time":0.4001769437,"remaining_time":0.6392436893},
{"learn":[4.208454294],"iteration":385,"passed_time":0.4009351753,"remaining_time":0.6377569887},
{"learn":[4.207446501],"iteration":386,"passed_time":0.4015857909,"remaining_time":0.6361035913},
{"learn":[4.204985442],"iteration":387,"passed_time":0.4022173783,"remaining_time":0.6344253493},
{"learn":[4.202796622],"iteration":388,"passed_time":0.4028984949,"remaining_time":0.6328302837},
{"learn":[4.199774004],"iteration":389,"passed_time":0.4035293108,"remaining_time":0.6311612296},
{"learn":[4.199458358],"iteration":390,"passed_time":0.4041535638,"remaining_time":0.6294872643},
{"learn":[4.19751254],"iteration":391,"passed_time":0.4047870402,"remaining_time":0.6278329603},
{"learn":[4.195201346],"iteration":392,"passed_time":0.4053814831,"remaining_time":0.6261235629},
{"learn":[4.190593508],"iteration":393,"passed_time":0.4059967978,"remaining_time":0.6244519276},
{"learn":[4.187212054],"iteration":394,"passed_time":0.4065410901,"remaining_time":0.6226768595},
{"learn":[4.184984466],"iteration":395,"passed_time":0.4071789501,"remaining_time":0.6210507219},
{"learn":[4.182832144],"iteration":396,"passed_time":0.4080168461,"remaining_time":0.619733396},
{"learn":[4.179752812],"iteration":397,"passed_time":0.4086850971,"remaining_time":0.6181618806},
{"learn":[4.17878934],"iteration":398,"passed_time":0.4094287498,"remaining_time":0.6167084677},
{"learn":[4.174548229],"iteration":399,"passed_time":0.4101120807,"remaining_time":0.6151681211},
{"learn":[4.168872556],"iteration":400,"passed_time":0.4108366198,"remaining_time":0.6136936042},
{"learn":[4.163926494],"iteration":401,"passed_time":0.4115143499,"remaining_time":0.6121531871},
{"learn":[4.159485076],"iteration":402,"passed_time":0.4121218891,"remaining_time":0.6105130714},
{"learn":[4.155926102],"iteration":403,"passed_time":0.4128320345,"remaining_time":0.609029437},
{"learn":[4.153540115],"iteration":404,"passed_time":0.4134998446,"remaining_time":0.607487426},
{"learn":[4.150983044],"iteration":405,"passed_time":0.4141673341,"remaining_time":0.6059492523},
{"learn":[4.146539132],"iteration":406,"passed_time":0.414908942,"remaining_time":0.6045233479},
{"learn":[4.144869174],"iteration":407,"passed_time":0.4156802401,"remaining_time":0.6031438778},
{"learn":[4.142825962],"iteration":408,"passed_time":0.4162933902,"remaining_time":0.6015388597},
{"learn":[4.142467378],"iteration":409,"passed_time":0.416890929,"remaining_time":0.5999162149},
{"learn":[4.141800768],"iteration":410,"passed_time":0.4175467454,"remaining_time":0.5983820755},
{"learn":[4.140107084],"iteration":411,"passed_time":0.4181508975,"remaining_time":0.5967784653},
{"learn":[4.136243196],"iteration":412,"passed_time":0.4187548595,"remaining_time":0.595179425},
{"learn":[4.133618439],"iteration":413,"passed_time":0.4194200847,"remaining_time":0.5936719073},
{"learn":[4.131053025],"iteration":414,"passed_time":0.4201781854,"remaining_time":0.5922993698},
{"learn":[4.128379975],"iteration":415,"passed_time":0.4208425793,"remaining_time":0.5907982363},
{"learn":[4.127068571],"iteration":416,"passed_time":0.4214552084,"remaining_time":0.5892287446},
{"learn":[4.125969877],"iteration":417,"passed_time":0.4222500137,"remaining_time":0.5879174832},
{"learn":[4.123893633],"iteration":418,"passed_time":0.4229576136,"remaining_time":0.586487765},
{"learn":[4.119643722],"iteration":419,"passed_time":0.4237237411,"remaining_time":0.5851423091},
{"learn":[4.11465686],"iteration":420,"passed_time":0.4244874637,"remaining_time":0.583796298},
{"learn":[4.111565986],"iteration":421,"passed_time":0.4251891715,"remaining_time":0.582368107},
{"learn":[4.106322452],"iteration":422,"passed_time":0.4259162609,"remaining_time":0.5809779729},
{"learn":[4.104222175],"iteration":423,"passed_time":0.4265156935,"remaining_time":0.5794175459},
{"learn":[4.103008002],"iteration":424,"passed_time":0.4270987138,"remaining_time":0.5778394363},
{"learn":[4.099176337],"iteration":425,"passed_time":0.4278980828,"remaining_time":0.5765575106},
{"learn":[4.096525716],"iteration":426,"passed_time":0.4286012539,"remaining_time":0.5751487552},
{"learn":[4.094967724],"iteration":427,"passed_time":0.4292555566,"remaining_time":0.5736779868},
{"learn":[4.094683584],"iteration":428,"passed_time":0.4298440075,"remaining_time":0.5721233759},
{"learn":[4.091096563],"iteration":429,"passed_time":0.430453731,"remaining_time":0.5706014574},
{"learn":[4.089178677],"iteration":430,"passed_time":0.4311409999,"remaining_time":0.569186146},
{"learn":[4.085335077],"iteration":431,"passed_time":0.4318372674,"remaining_time":0.5677860368},
{"learn":[4.084852122],"iteration":432,"passed_time":0.4324395861,"remaining_time":0.5662661555},
{"learn":[4.080322952],"iteration":433,"passed_time":0.4331251218,"remaining_time":0.5648590299},
{"learn":[4.077449519],"iteration":434,"passed_time":0.4338481227,"remaining_time":0.5635038835},
{"learn":[4.076568374],"iteration":435,"passed_time":0.4344280662,"remaining_time":0.5619665811},
{"learn":[4.076071793],"iteration":436,"passed_time":0.4351042535,"remaining_time":0.5605576538},
{"learn":[4.075027644],"iteration":437,"passed_time":0.4357603601,"remaining_time":0.5591263068},
{"learn":[4.07020837],"iteration":438,"passed_time":0.4366341436,"remaining_time":0.5579766618},
{"learn":[4.06833694],"iteration":439,"passed_time":0.4372759266,"remaining_time":0.5565329975},
{"learn":[4.063936568],"iteration":440,"passed_time":0.4379326691,"remaining_time":0.555111932},
{"learn":[4.061734926],"iteration":441,"passed_time":0.4386605051,"remaining_time":0.5537840766},
{"learn":[4.060815619],"iteration":442,"passed_time":0.4393213112,"remaining_time":0.5523746509},
{"learn":[4.056407489],"iteration":443,"passed_time":0.4399118611,"remaining_time":0.5508806189},
{"learn":[4.05238936],"iteration":444,"passed_time":0.4405607083,"remaining_time":0.5494633554},
{"learn":[4.049685254],"iteration":445,"passed_time":0.4412070302,"remaining_time":0.5480464007},
{"learn":[4.045162016],"iteration":446,"passed_time":0.4419253417,"remaining_time":0.5467219551},
{"learn":[4.042955482],"iteration":447,"passed_time":0.4425226203,"remaining_time":0.5452510857},
{"learn":[4.041467663],"iteration":448,"passed_time":0.4431694884,"remaining_time":0.5438449623},
{"learn":[4.038920476],"iteration":449,"passed_time":0.4437996429,"remaining_time":0.5424217858},
{"learn":[4.036694383],"iteration":450,"passed_time":0.4444858849,"remaining_time":0.5410704009},
{"learn":[4.034999007],"iteration":451,"passed_time":0.4451716714,"remaining_time":0.5397214069},
{"learn":[4.031928018],"iteration":452,"passed_time":0.4459233097,"remaining_time":0.5384548575},
{"learn":[4.028718143],"iteration":453,"passed_time":0.4466468815,"remaining_time":0.5371568222},
{"learn":[4.027401978],"iteration":454,"passed_time":0.4472250821,"remaining_time":0.5356871862},
{"learn":[4.025930598],"iteration":455,"passed_time":0.4478510282,"remaining_time":0.5342784196},
{"learn":[4.021074523],"iteration":456,"passed_time":0.4486254468,"remaining_time":0.5330494915},
{"learn":[4.020268486],"iteration":457,"passed_time":0.4493432172,"remaining_time":0.5317555103},
{"learn":[4.017986361],"iteration":458,"passed_time":0.4500035824,"remaining_time":0.5303963792},
{"learn":[4.014814804],"iteration":459,"passed_time":0.4506536223,"remaining_time":0.5290281653},
{"learn":[4.009704796],"iteration":460,"passed_time":0.4513426098,"remaining_time":0.5277086045},
{"learn":[4.008440457],"iteration":461,"passed_time":0.4523079069,"remaining_time":0.5267135366},
{"learn":[4.004854849],"iteration":462,"passed_time":0.4529590533,"remaining_time":0.5253542367},
{"learn":[4.000898028],"iteration":463,"passed_time":0.4536296693,"remaining_time":0.5240204801},
{"learn":[3.996617985],"iteration":464,"passed_time":0.4543178801,"remaining_time":0.522709819},
{"learn":[3.995443319],"iteration":465,"passed_time":0.4549473536,"remaining_time":0.5213345211},
{"learn":[3.990771995],"iteration":466,"passed_time":0.4555938962,"remaining_time":0.5199818987},
{"learn":[3.989249359],"iteration":467,"passed_time":0.4562569267,"remaining_time":0.5186510364},
{"learn":[3.986599538],"iteration":468,"passed_time":0.4569961423,"remaining_time":0.5174092783},
{"learn":[3.985628919],"iteration":469,"passed_time":0.457578579,"remaining_time":0.5159928656},
{"learn":[3.985086112],"iteration":470,"passed_time":0.4582886739,"remaining_time":0.5147233726},
{"learn":[3.98466839],"iteration":471,"passed_time":0.4589338386,"remaining_time":0.5133836161},
{"learn":[3.984233894],"iteration":472,"passed_time":0.4594935919,"remaining_time":0.5119516341},
{"learn":[3.981855845],"iteration":473,"passed_time":0.4601383858,"remaining_time":0.5106177024},
{"learn":[3.978684264],"iteration":474,"passed_time":0.4608248826,"remaining_time":0.5093327649},
{"learn":[3.974361269],"iteration":475,"passed_time":0.4613794955,"remaining_time":0.5079051589},
{"learn":[3.972074049],"iteration":476,"passed_time":0.4619256215,"remaining_time":0.5064719078},
{"learn":[3.97191982],"iteration":477,"passed_time":0.4624737314,"remaining_time":0.5050445351},
{"learn":[3.969616848],"iteration":478,"passed_time":0.4630978359,"remaining_time":0.5037034917},
{"learn":[3.968533527],"iteration":479,"passed_time":0.4636682983,"remaining_time":0.5023073231},
{"learn":[3.967568753],"iteration":480,"passed_time":0.464210619,"remaining_time":0.500884223},
{"learn":[3.966232553],"iteration":481,"passed_time":0.4649300928,"remaining_time":0.499655162},
{"learn":[3.961522393],"iteration":482,"passed_time":0.4656034337,"remaining_time":0.4983788307},
{"learn":[3.955829553],"iteration":483,"passed_time":0.4661551208,"remaining_time":0.4969752941},
{"learn":[3.954248095],"iteration":484,"passed_time":0.4666603447,"remaining_time":0.495525933},
{"learn":[3.951922606],"iteration":485,"passed_time":0.4672184149,"remaining_time":0.4941363483},
{"learn":[3.94978202],"iteration":486,"passed_time":0.4677891001,"remaining_time":0.4927634669},
{"learn":[3.949518999],"iteration":487,"passed_time":0.4683556273,"remaining_time":0.4913895106},
{"learn":[3.945431216],"iteration":488,"passed_time":0.4689551024,"remaining_time":0.490053287},
{"learn":[3.943249086],"iteration":489,"passed_time":0.4695267071,"remaining_time":0.4886910625},
{"learn":[3.941981548],"iteration":490,"passed_time":0.4701106793,"remaining_time":0.4873448793},
{"learn":[3.936600517],"iteration":491,"passed_time":0.4707549743,"remaining_time":0.4860640792},
{"learn":[3.934476885],"iteration":492,"passed_time":0.471370277,"remaining_time":0.4847560455},
{"learn":[3.93045798],"iteration":493,"passed_time":0.4718998096,"remaining_time":0.4833629629},
{"learn":[3.925977375],"iteration":494,"passed_time":0.4724844027,"remaining_time":0.4820295422},
{"learn":[3.92457993],"iteration":495,"passed_time":0.4731227458,"remaining_time":0.4807537579},
{"learn":[3.919849146],"iteration":496,"passed_time":0.4736915673,"remaining_time":0.4794101778},
{"learn":[3.919681964],"iteration":497,"passed_time":0.474230777,"remaining_time":0.4780398595},
{"learn":[3.917633027],"iteration":498,"passed_time":0.4748520737,"remaining_time":0.4767552885},
{"learn":[3.916616419],"iteration":499,"passed_time":0.475463962,"remaining_time":0.475463962},
{"learn":[3.912896166],"iteration":500,"passed_time":0.476029226,"remaining_time":0.4741289097},
{"learn":[3.912769674],"iteration":501,"passed_time":0.4765988093,"remaining_time":0.4728012092},
{"learn":[3.909373788],"iteration":502,"passed_time":0.4772024106,"remaining_time":0.4715101353},
{"learn":[3.906706036],"iteration":503,"passed_time":0.4777504203,"remaining_time":0.4701670803},
{"learn":[3.903895664],"iteration":504,"passed_time":0.4783421156,"remaining_time":0.4688699945},
{"learn":[3.902982967],"iteration":505,"passed_time":0.4788716282,"remaining_time":0.4675149888},
{"learn":[3.900905528],"iteration":506,"passed_time":0.4794229044,"remaining_time":0.4661844021},
{"learn":[3.897463465],"iteration":507,"passed_time":0.4799382185,"remaining_time":0.4648220542},
{"learn":[3.895918033],"iteration":508,"passed_time":0.4805686737,"remaining_time":0.4635741037},
{"learn":[3.893921936],"iteration":509,"passed_time":0.48116481,"remaining_time":0.4622956018},
{"learn":[3.890237934],"iteration":510,"passed_time":0.4817205352,"remaining_time":0.4609810993},
{"learn":[3.887311613],"iteration":511,"passed_time":0.4824117119,"remaining_time":0.4597986629},
{"learn":[3.884869735],"iteration":512,"passed_time":0.4830658249,"remaining_time":0.4585829566},
{"learn":[3.882101231],"iteration":513,"passed_time":0.483659526,"remaining_time":0.4573123144},
{"learn":[3.88060368],"iteration":514,"passed_time":0.4842601813,"remaining_time":0.4560508504},
{"learn":[3.877726076],"iteration":515,"passed_time":0.4848423496,"remaining_time":0.454774607},
{"learn":[3.874938145],"iteration":516,"passed_time":0.4855170739,"remaining_time":0.4535875178},
{"learn":[3.874340833],"iteration":517,"passed_time":0.4860879395,"remaining_time":0.4523057661},
{"learn":[3.873105224],"iteration":518,"passed_time":0.4866732237,"remaining_time":0.4510401168},
{"learn":[3.869800236],"iteration":519,"passed_time":0.4872366644,"remaining_time":0.449756921},
{"learn":[3.867932518],"iteration":520,"passed_time":0.4878708795,"remaining_time":0.4485415572},
{"learn":[3.866666962],"iteration":521,"passed_time":0.4884353423,"remaining_time":0.4472645471},
{"learn":[3.865527652],"iteration":522,"passed_time":0.4890086427,"remaining_time":0.4459983223},
{"learn":[3.861900081],"iteration":523,"passed_time":0.4895661215,"remaining_time":0.4447203699},
{"learn":[3.858502887],"iteration":524,"passed_time":0.4901151232,"remaining_time":0.4434374924},
{"learn":[3.858335097],"iteration":525,"passed_time":0.4906907583,"remaining_time":0.4421814058},
{"learn":[3.855719306],"iteration":526,"passed_time":0.4912815017,"remaining_time":0.4409414617},
{"learn":[3.855137428],"iteration":527,"passed_time":0.4918639502,"remaining_time":0.4396965615},
{"learn":[3.851985706],"iteration":528,"passed_time":0.4924236437,"remaining_time":0.4384339058},
{"learn":[3.851051809],"iteration":529,"passed_time":0.4932328396,"remaining_time":0.4373951597},
{"learn":[3.850679146],"iteration":530,"passed_time":0.4938330921,"remaining_time":0.436172731},
{"learn":[3.848179484],"iteration":531,"passed_time":0.4943490174,"remaining_time":0.4348784589},
{"learn":[3.844551071],"iteration":532,"passed_time":0.4949848956,"remaining_time":0.4336922068},
{"learn":[3.841604794],"iteration":533,"passed_time":0.4955781136,"remaining_time":0.4324707883},
{"learn":[3.83969656],"iteration":534,"passed_time":0.4961778872,"remaining_time":0.431257416},
{"learn":[3.836811463],"iteration":535,"passed_time":0.4967663381,"remaining_time":0.4300365315},
{"learn":[3.834182551],"iteration":536,"passed_time":0.4974009716,"remaining_time":0.428857821},
{"learn":[3.828012842],"iteration":537,"passed_time":0.4981026421,"remaining_time":0.4277387001},
{"learn":[3.826636176],"iteration":538,"passed_time":0.4987159504,"remaining_time":0.4265455532},
{"learn":[3.826189798],"iteration":539,"passed_time":0.4993035296,"remaining_time":0.4253326363},
{"learn":[3.824104738],"iteration":540,"passed_time":0.4998998465,"remaining_time":0.4241294447},
{"learn":[3.82300218],"iteration":541,"passed_time":0.5004274754,"remaining_time":0.4228704497},
{"learn":[3.817146402],"iteration":542,"passed_time":0.5009984308,"remaining_time":0.421650613},
{"learn":[3.814638044],"iteration":543,"passed_time":0.5015819418,"remaining_time":0.4204436865},
{"learn":[3.812979573],"iteration":544,"passed_time":0.5021155827,"remaining_time":0.419197413},
{"learn":[3.811938825],"iteration":545,"passed_time":0.502640837,"remaining_time":0.4179467766},
{"learn":[3.811479418],"iteration":546,"passed_time":0.5032786767,"remaining_time":0.4167920302},
{"learn":[3.80742981],"iteration":547,"passed_time":0.5039343822,"remaining_time":0.4156539065},
{"learn":[3.805097043],"iteration":548,"passed_time":0.5045443062,"remaining_time":0.414479931},
{"learn":[3.801577232],"iteration":549,"passed_time":0.505144974,"remaining_time":0.4133004333},
{"learn":[3.799762083],"iteration":550,"passed_time":0.5057769398,"remaining_time":0.4121485408},
{"learn":[3.796393455],"iteration":551,"passed_time":0.5063620263,"remaining_time":0.4109604851},
{"learn":[3.793486459],"iteration":552,"passed_time":0.5071650278,"remaining_time":0.4099507548},
{"learn":[3.792006091],"iteration":553,"passed_time":0.5078474372,"remaining_time":0.4088446877},
{"learn":[3.78932128],"iteration":554,"passed_time":0.5084984232,"remaining_time":0.407714952},
{"learn":[3.787581812],"iteration":555,"passed_time":0.5091669351,"remaining_time":0.4066009338},
{"learn":[3.785308865],"iteration":556,"passed_time":0.5097941234,"remaining_time":0.4054556493},
{"learn":[3.78465475],"iteration":557,"passed_time":0.5103487868,"remaining_time":0.4042547737},
{"learn":[3.780498869],"iteration":558,"passed_time":0.5109700034,"remaining_time":0.4031087147},
{"learn":[3.778734909],"iteration":559,"passed_time":0.5115422217,"remaining_time":0.4019260313},
{"learn":[3.778652349],"iteration":560,"passed_time":0.5120520748,"remaining_time":0.4006967217},
{"learn":[3.777928006],"iteration":561,"passed_time":0.5126251445,"remaining_time":0.3995192408},
{"learn":[3.776131406],"iteration":562,"passed_time":0.513276051,"remaining_time":0.3984043238},
{"learn":[3.772925617],"iteration":563,"passed_time":0.5138489103,"remaining_time":0.3972307179},
{"learn":[3.7727745],"iteration":564,"passed_time":0.5144312714,"remaining_time":0.3960665541},
{"learn":[3.771763073],"iteration":565,"passed_time":0.5149967662,"remaining_time":0.3948915133},
{"learn":[3.768738162],"iteration":566,"passed_time":0.5155990928,"remaining_time":0.3937467499},
{"learn":[3.767220794],"iteration":567,"passed_time":0.5162094777,"remaining_time":0.3926100253},
{"learn":[3.766691102],"iteration":568,"passed_time":0.5167737197,"remaining_time":0.3914401989},
{"learn":[3.766259335],"iteration":569,"passed_time":0.5173436236,"remaining_time":0.3902767687},
{"learn":[3.76116362],"iteration":570,"passed_time":0.5179204333,"remaining_time":0.3891206057},
{"learn":[3.758633056],"iteration":571,"passed_time":0.5185925199,"remaining_time":0.3880377596},
{"learn":[3.754603809],"iteration":572,"passed_time":0.5191713514,"remaining_time":0.3868868535},
{"learn":[3.754070549],"iteration":573,"passed_time":0.5196989602,"remaining_time":0.3856999252},
{"learn":[3.750534319],"iteration":574,"passed_time":0.5202426112,"remaining_time":0.3845271474},
{"learn":[3.746491516],"iteration":575,"passed_time":0.5207893283,"remaining_time":0.3833588111},
{"learn":[3.744210544],"iteration":576,"passed_time":0.5214765471,"remaining_time":0.3822956316},
{"learn":[3.742929991],"iteration":577,"passed_time":0.5220612705,"remaining_time":0.3811589207},
{"learn":[3.740402992],"iteration":578,"passed_time":0.5226441301,"remaining_time":0.3800227613},
{"learn":[3.739644243],"iteration":579,"passed_time":0.523201208,"remaining_time":0.3788698403},
{"learn":[3.737529404],"iteration":580,"passed_time":0.5237684965,"remaining_time":0.3777263339},
{"learn":[3.737196923],"iteration":581,"passed_time":0.5243260353,"remaining_time":0.3765778054},
{"learn":[3.733954464],"iteration":582,"passed_time":0.5248535739,"remaining_time":0.3754098462},
{"learn":[3.731608623],"iteration":583,"passed_time":0.5254089785,"remaining_time":0.3742639299},
{"learn":[3.729843952],"iteration":584,"passed_time":0.5259906658,"remaining_time":0.3731386774},
{"learn":[3.727223798],"iteration":585,"passed_time":0.5265458198,"remaining_time":0.3719965348},
{"learn":[3.725351667],"iteration":586,"passed_time":0.5270993005,"remaining_time":0.3708552149},
{"learn":[3.725026912],"iteration":587,"passed_time":0.5276669196,"remaining_time":0.3697258008},
{"learn":[3.721974565],"iteration":588,"passed_time":0.5282927658,"remaining_time":0.3686389249},
{"learn":[3.720269493],"iteration":589,"passed_time":0.528911778,"remaining_time":0.3675488627},
{"learn":[3.718907466],"iteration":590,"passed_time":0.5294637758,"remaining_time":0.3664140174},
{"learn":[3.715602912],"iteration":591,"passed_time":0.5300743811,"remaining_time":0.3653215329},
{"learn":[3.714463059],"iteration":592,"passed_time":0.5306630421,"remaining_time":0.3642156124},
{"learn":[3.710802077],"iteration":593,"passed_time":0.531222485,"remaining_time":0.3630914628},
{"learn":[3.708032435],"iteration":594,"passed_time":0.5318184109,"remaining_time":0.3619940444},
{"learn":[3.703788939],"iteration":595,"passed_time":0.532392503,"remaining_time":0.3608835087},
{"learn":[3.702500944],"iteration":596,"passed_time":0.5329589497,"remaining_time":0.3597696093},
{"learn":[3.698196925],"iteration":597,"passed_time":0.5335326409,"remaining_time":0.3586624108},
{"learn":[3.69658891],"iteration":598,"passed_time":0.5340986869,"remaining_time":0.3575518755},
{"learn":[3.696124066],"iteration":599,"passed_time":0.5346802937,"remaining_time":0.3564535291},
{"learn":[3.693537052],"iteration":600,"passed_time":0.5353308993,"remaining_time":0.3554027102},
{"learn":[3.691343275],"iteration":601,"passed_time":0.5359193101,"remaining_time":0.354312102},
{"learn":[3.690973831],"iteration":602,"passed_time":0.5364879816,"remaining_time":0.3532101637},
{"learn":[3.686151073],"iteration":603,"passed_time":0.5370456807,"remaining_time":0.3521027973},
{"learn":[3.683921982],"iteration":604,"passed_time":0.5376081294,"remaining_time":0.351000349},
{"learn":[3.679975271],"iteration":605,"passed_time":0.5382388573,"remaining_time":0.3499440755},
{"learn":[3.674047638],"iteration":606,"passed_time":0.5388756852,"remaining_time":0.3488931537},
{"learn":[3.673151794],"iteration":607,"passed_time":0.5395351565,"remaining_time":0.347858193},
{"learn":[3.670953108],"iteration":608,"passed_time":0.5401812931,"remaining_time":0.3468159041},
{"learn":[3.6703947],"iteration":609,"passed_time":0.5408656565,"remaining_time":0.3457993541},
{"learn":[3.668433805],"iteration":610,"passed_time":0.5414375641,"remaining_time":0.3447122953},
{"learn":[3.668304956],"iteration":611,"passed_time":0.5419986823,"remaining_time":0.3436200796},
{"learn":[3.667880012],"iteration":612,"passed_time":0.5425370426,"remaining_time":0.3425152292},
{"learn":[3.667282264],"iteration":613,"passed_time":0.5430781485,"remaining_time":0.34141395},
{"learn":[3.664611483],"iteration":614,"passed_time":0.5437364975,"remaining_time":0.3403878887},
{"learn":[3.662543394],"iteration":615,"passed_time":0.5443605921,"remaining_time":0.3393416678},
{"learn":[3.659041959],"iteration":616,"passed_time":0.5449699027,"remaining_time":0.3382876381},
{"learn":[3.656868545],"iteration":617,"passed_time":0.5455900371,"remaining_time":0.3372417382},
{"learn":[3.654785614],"iteration":618,"passed_time":0.546240715,"remaining_time":0.3362160136},
{"learn":[3.654566096],"iteration":619,"passed_time":0.5468547551,"remaining_time":0.3351690434},
{"learn":[3.651007045],"iteration":620,"passed_time":0.5474336468,"remaining_time":0.3341020163},
{"learn":[3.648921786],"iteration":621,"passed_time":0.5480218572,"remaining_time":0.3330422219},
{"learn":[3.647655706],"iteration":622,"passed_time":0.5487026977,"remaining_time":0.3320399952},
{"learn":[3.647241144],"iteration":623,"passed_time":0.5493127316,"remaining_time":0.3309961331},
{"learn":[3.644195689],"iteration":624,"passed_time":0.5499218339,"remaining_time":0.3299531003},
{"learn":[3.642632246],"iteration":625,"passed_time":0.5504796135,"remaining_time":0.3288807915},
{"learn":[3.642523322],"iteration":626,"passed_time":0.550932963,"remaining_time":0.3277479987},
{"learn":[3.641494659],"iteration":627,"passed_time":0.5515189191,"remaining_time":0.3266959203},
{"learn":[3.63976496],"iteration":628,"passed_time":0.5521021295,"remaining_time":0.3256437044},
{"learn":[3.637945652],"iteration":629,"passed_time":0.5527002398,"remaining_time":0.3246017281},
{"learn":[3.636233667],"iteration":630,"passed_time":0.5533056647,"remaining_time":0.3235654362},
{"learn":[3.635304404],"iteration":631,"passed_time":0.5538904178,"remaining_time":0.3225184712},
{"learn":[3.632234951],"iteration":632,"passed_time":0.5544449409,"remaining_time":0.3214554397},
{"learn":[3.631630987],"iteration":633,"passed_time":0.5550291132,"remaining_time":0.3204111285},
{"learn":[3.630301009],"iteration":634,"passed_time":0.5556129749,"remaining_time":0.3193680879},
{"learn":[3.629077964],"iteration":635,"passed_time":0.5562400633,"remaining_time":0.3183512312},
{"learn":[3.628004522],"iteration":636,"passed_time":0.5568565204,"remaining_time":0.3173295399},
{"learn":[3.625062876],"iteration":637,"passed_time":0.5574771258,"remaining_time":0.3163114726},
{"learn":[3.624917986],"iteration":638,"passed_time":0.5580870497,"remaining_time":0.315288615},
{"learn":[3.622887087],"iteration":639,"passed_time":0.5586701499,"remaining_time":0.3142519593},
{"learn":[3.621220865],"iteration":640,"passed_time":0.559277308,"remaining_time":0.3132301928},
{"learn":[3.621143844],"iteration":641,"passed_time":0.5598687251,"remaining_time":0.3122009402},
{"learn":[3.620822821],"iteration":642,"passed_time":0.5604260736,"remaining_time":0.3111541342},
{"learn":[3.619202826],"iteration":643,"passed_time":0.5610268492,"remaining_time":0.3101328545},
{"learn":[3.618204882],"iteration":644,"passed_time":0.5616061514,"remaining_time":0.3091010601},
{"learn":[3.614259666],"iteration":645,"passed_time":0.5623078097,"remaining_time":0.3081377162},
{"learn":[3.613415661],"iteration":646,"passed_time":0.5629710917,"remaining_time":0.3071542432},
{"learn":[3.611096773],"iteration":647,"passed_time":0.5636018019,"remaining_time":0.3061540652},
{"learn":[3.610820695],"iteration":648,"passed_time":0.564158755,"remaining_time":0.3051151356},
{"learn":[3.609290065],"iteration":649,"passed_time":0.5647422405,"remaining_time":0.3040919757},
{"learn":[3.60897947],"iteration":650,"passed_time":0.5652990934,"remaining_time":0.3030558888},
{"learn":[3.606570702],"iteration":651,"passed_time":0.5659708815,"remaining_time":0.3020826177},
{"learn":[3.606292637],"iteration":652,"passed_time":0.5665640819,"remaining_time":0.3010685091},
{"learn":[3.602753838],"iteration":653,"passed_time":0.5671646617,"remaining_time":0.3000595917},
{"learn":[3.599755869],"iteration":654,"passed_time":0.5677358834,"remaining_time":0.2990364577},
{"learn":[3.599509575],"iteration":655,"passed_time":0.56834469,"remaining_time":0.2980344106},
{"learn":[3.595337722],"iteration":656,"passed_time":0.5689336416,"remaining_time":0.2970231949},
{"learn":[3.595168561],"iteration":657,"passed_time":0.5695190312,"remaining_time":0.2960114113},
{"learn":[3.59290559],"iteration":658,"passed_time":0.570155223,"remaining_time":0.2950272095},
{"learn":[3.592015928],"iteration":659,"passed_time":0.5708602026,"remaining_time":0.2940794983},
{"learn":[3.590680403],"iteration":660,"passed_time":0.5714076563,"remaining_time":0.293051733},
{"learn":[3.590361532],"iteration":661,"passed_time":0.5719821638,"remaining_time":0.2920392316},
{"learn":[3.589069739],"iteration":662,"passed_time":0.5726186207,"remaining_time":0.2910595402},
{"learn":[3.585010186],"iteration":663,"passed_time":0.5732397274,"remaining_time":0.2900731151},
{"learn":[3.582997552],"iteration":664,"passed_time":0.5738750523,"remaining_time":0.2890949512},
{"learn":[3.582119256],"iteration":665,"passed_time":0.5745379222,"remaining_time":0.2881316307},
{"learn":[3.579019356],"iteration":666,"passed_time":0.5752119451,"remaining_time":0.2871747792},
{"learn":[3.57719559],"iteration":667,"passed_time":0.5758897653,"remaining_time":0.2862206618},
{"learn":[3.574050046],"iteration":668,"passed_time":0.5765148698,"remaining_time":0.2852412883},
{"learn":[3.572204518],"iteration":669,"passed_time":0.5772421192,"remaining_time":0.2843132826},
{"learn":[3.569508025],"iteration":670,"passed_time":0.5779435768,"remaining_time":0.2833732292},
{"learn":[3.566268704],"iteration":671,"passed_time":0.5785910261,"remaining_time":0.2824075246},
{"learn":[3.562564052],"iteration":672,"passed_time":0.5792157898,"remaining_time":0.2814317433},
{"learn":[3.561173586],"iteration":673,"passed_time":0.5798161898,"remaining_time":0.2804452194},
{"learn":[3.559551904],"iteration":674,"passed_time":0.5804030824,"remaining_time":0.279453336},
{"learn":[3.558593054],"iteration":675,"passed_time":0.5810648477,"remaining_time":0.2784985365},
{"learn":[3.555647008],"iteration":676,"passed_time":0.5816604906,"remaining_time":0.2775130553},
{"learn":[3.553100059],"iteration":677,"passed_time":0.5822601543,"remaining_time":0.2765306337},
{"learn":[3.55085578],"iteration":678,"passed_time":0.5828495792,"remaining_time":0.2755444992},
{"learn":[3.550737965],"iteration":679,"passed_time":0.5834520859,"remaining_time":0.2745656875},
{"learn":[3.549408772],"iteration":680,"passed_time":0.5840934854,"remaining_time":0.2736061995},
{"learn":[3.547390589],"iteration":681,"passed_time":0.5846836075,"remaining_time":0.2726237349},
{"learn":[3.54723575],"iteration":682,"passed_time":0.5852243023,"remaining_time":0.2716194785},
{"learn":[3.543988891],"iteration":683,"passed_time":0.5858135951,"remaining_time":0.2706390293},
{"learn":[3.543868508],"iteration":684,"passed_time":0.5863529696,"remaining_time":0.2696367671},
{"learn":[3.542752124],"iteration":685,"passed_time":0.5869683725,"remaining_time":0.2686706545},
{"learn":[3.541334315],"iteration":686,"passed_time":0.5875761142,"remaining_time":0.2677020724},
{"learn":[3.540208266],"iteration":687,"passed_time":0.5882115694,"remaining_time":0.266747107},
{"learn":[3.537730983],"iteration":688,"passed_time":0.5888837483,"remaining_time":0.2658096454},
{"learn":[3.53419867],"iteration":689,"passed_time":0.5894811969,"remaining_time":0.2648393783},
{"learn":[3.532628335],"iteration":690,"passed_time":0.590304319,"remaining_time":0.2639711065},
{"learn":[3.532204987],"iteration":691,"passed_time":0.591050657,"remaining_time":0.2630687895},
{"learn":[3.530618147],"iteration":692,"passed_time":0.5916219234,"remaining_time":0.2620893658},
{"learn":[3.528909306],"iteration":693,"passed_time":0.59223315,"remaining_time":0.2611287376},
{"learn":[3.526700678],"iteration":694,"passed_time":0.5929231495,"remaining_time":0.2602036843},
{"learn":[3.526439574],"iteration":695,"passed_time":0.5935049771,"remaining_time":0.259232059},
{"learn":[3.525784216],"iteration":696,"passed_time":0.5940662987,"remaining_time":0.2582526377},
{"learn":[3.524112693],"iteration":697,"passed_time":0.5947145796,"remaining_time":0.2573120387},
{"learn":[3.522813541],"iteration":698,"passed_time":0.59527546,"remaining_time":0.2563346401},
{"learn":[3.519148203],"iteration":699,"passed_time":0.5958438005,"remaining_time":0.2553616288},
{"learn":[3.517236747],"iteration":700,"passed_time":0.5964670011,"remaining_time":0.2544131717},
{"learn":[3.515603888],"iteration":701,"passed_time":0.597089245,"remaining_time":0.253465235},
{"learn":[3.51263524],"iteration":702,"passed_time":0.5977399508,"remaining_time":0.2525302495},
{"learn":[3.51123442],"iteration":703,"passed_time":0.5982899694,"remaining_time":0.2515537371},
{"learn":[3.50828027],"iteration":704,"passed_time":0.59887348,"remaining_time":0.2505924491},
{"learn":[3.508265537],"iteration":705,"passed_time":0.5992510932,"remaining_time":0.2495464893},
{"learn":[3.506774876],"iteration":706,"passed_time":0.5998451454,"remaining_time":0.2485921182},
{"learn":[3.50552068],"iteration":707,"passed_time":0.6004224739,"remaining_time":0.2476318678},
{"learn":[3.501973993],"iteration":708,"passed_time":0.6010462104,"remaining_time":0.246691745},
{"learn":[3.498880354],"iteration":709,"passed_time":0.6016165547,"remaining_time":0.2457307054},
{"learn":[3.497370959],"iteration":710,"passed_time":0.60219712,"remaining_time":0.2447749194},
{"learn":[3.496050455],"iteration":711,"passed_time":0.6027537467,"remaining_time":0.2438105043},
{"learn":[3.495630067],"iteration":712,"passed_time":0.6033399434,"remaining_time":0.2428591357},
{"learn":[3.49550669],"iteration":713,"passed_time":0.6038972217,"remaining_time":0.2418972065},
{"learn":[3.493652375],"iteration":714,"passed_time":0.6046531186,"remaining_time":0.2410155787},
{"learn":[3.491915684],"iteration":715,"passed_time":0.6052480825,"remaining_time":0.2400704685},
{"learn":[3.490303956],"iteration":716,"passed_time":0.6058320745,"remaining_time":0.2391220043},
{"learn":[3.488363853],"iteration":717,"passed_time":0.6064246135,"remaining_time":0.2381779123},
{"learn":[3.485483936],"iteration":718,"passed_time":0.6070051986,"remaining_time":0.2372301263},
{"learn":[3.483763466],"iteration":719,"passed_time":0.6075908837,"remaining_time":0.2362853436},
{"learn":[3.481642352],"iteration":720,"passed_time":0.6081792246,"remaining_time":0.2353425848},
{"learn":[3.479826119],"iteration":721,"passed_time":0.6087961927,"remaining_time":0.2344118304},
{"learn":[3.478588728],"iteration":722,"passed_time":0.609360946,"remaining_time":0.2334619392},
{"learn":[3.475390887],"iteration":723,"passed_time":0.6099515412,"remaining_time":0.2325229632},
{"learn":[3.472636852],"iteration":724,"passed_time":0.6104979277,"remaining_time":0.2315681795},
{"learn":[3.47061883],"iteration":725,"passed_time":0.6110826161,"remaining_time":0.2306289763},
{"learn":[3.46953149],"iteration":726,"passed_time":0.6116409511,"remaining_time":0.2296808523},
{"learn":[3.467217162],"iteration":727,"passed_time":0.6122049283,"remaining_time":0.2287359073},
{"learn":[3.465686216],"iteration":728,"passed_time":0.6128376426,"remaining_time":0.2278175599},
{"learn":[3.462631216],"iteration":729,"passed_time":0.6134265343,"remaining_time":0.2268837867},
{"learn":[3.461451053],"iteration":730,"passed_time":0.6139801007,"remaining_time":0.2259379577},
{"learn":[3.458950469],"iteration":731,"passed_time":0.6145852699,"remaining_time":0.2250120934},
{"learn":[3.458072145],"iteration":732,"passed_time":0.6151923379,"remaining_time":0.2240877957},
{"learn":[3.454364268],"iteration":733,"passed_time":0.6158257693,"remaining_time":0.2231739164},
{"learn":[3.453243406],"iteration":734,"passed_time":0.6164160991,"remaining_time":0.2222452602},
{"learn":[3.453017963],"iteration":735,"passed_time":0.6169962181,"remaining_time":0.2213138608},
{"learn":[3.45201581],"iteration":736,"passed_time":0.6176401603,"remaining_time":0.2204061902},
{"learn":[3.449510107],"iteration":737,"passed_time":0.6183130704,"remaining_time":0.2195095182},
{"learn":[3.447189189],"iteration":738,"passed_time":0.6188826634,"remaining_time":0.2185769623},
{"learn":[3.446423605],"iteration":739,"passed_time":0.6195132744,"remaining_time":0.2176668261},
{"learn":[3.445531987],"iteration":740,"passed_time":0.6200542949,"remaining_time":0.2167261301},
{"learn":[3.445328199],"iteration":741,"passed_time":0.6206314328,"remaining_time":0.2157990696},
{"learn":[3.443327544],"iteration":742,"passed_time":0.6212745136,"remaining_time":0.2148957604},
{"learn":[3.441475798],"iteration":743,"passed_time":0.6218346728,"remaining_time":0.2139646186},
{"learn":[3.439046501],"iteration":744,"passed_time":0.622433214,"remaining_time":0.2130476101},
{"learn":[3.435899469],"iteration":745,"passed_time":0.6229535381,"remaining_time":0.212104824},
{"learn":[3.433988352],"iteration":746,"passed_time":0.6235228755,"remaining_time":0.2111797691},
{"learn":[3.433413263],"iteration":747,"passed_time":0.6241887314,"remaining_time":0.2102881822},
{"learn":[3.429944699],"iteration":748,"passed_time":0.6247733901,"remaining_time":0.2093699879},
{"learn":[3.429291634],"iteration":749,"passed_time":0.6253586093,"remaining_time":0.2084528698},
{"learn":[3.429175603],"iteration":750,"passed_time":0.6258712982,"remaining_time":0.2075125875},
{"learn":[3.428780323],"iteration":751,"passed_time":0.6264657611,"remaining_time":0.2066004106},
{"learn":[3.423893341],"iteration":752,"passed_time":0.6270774438,"remaining_time":0.2056947259},
{"learn":[3.421024316],"iteration":753,"passed_time":0.6276475123,"remaining_time":0.2047762441},
{"learn":[3.420969872],"iteration":754,"passed_time":0.6281868549,"remaining_time":0.2038487145},
{"learn":[3.419544785],"iteration":755,"passed_time":0.6287452552,"remaining_time":0.2029283628},
{"learn":[3.417057977],"iteration":756,"passed_time":0.6293350943,"remaining_time":0.2020190593},
{"learn":[3.415160245],"iteration":757,"passed_time":0.6299177283,"remaining_time":0.2011082985},
{"learn":[3.412854597],"iteration":758,"passed_time":0.6304815349,"remaining_time":0.2001924241},
{"learn":[3.410926347],"iteration":759,"passed_time":0.6310335074,"remaining_time":0.1992737392},
{"learn":[3.408963843],"iteration":760,"passed_time":0.6316210462,"remaining_time":0.198367188},
{"learn":[3.407629634],"iteration":761,"passed_time":0.6323055401,"remaining_time":0.1974917566},
{"learn":[3.404384724],"iteration":762,"passed_time":0.6329057643,"remaining_time":0.1965906502},
{"learn":[3.403041656],"iteration":763,"passed_time":0.6334828426,"remaining_time":0.1956831818},
{"learn":[3.401101731],"iteration":764,"passed_time":0.6340906976,"remaining_time":0.1947860313},
{"learn":[3.400890668],"iteration":765,"passed_time":0.6346107512,"remaining_time":0.1938628143},
{"learn":[3.399289941],"iteration":766,"passed_time":0.6351896377,"remaining_time":0.192958521},
{"learn":[3.399202366],"iteration":767,"passed_time":0.6357236594,"remaining_time":0.1920415221},
{"learn":[3.397447845],"iteration":768,"passed_time":0.6363492946,"remaining_time":0.1911530391},
{"learn":[3.394655341],"iteration":769,"passed_time":0.6369608121,"remaining_time":0.1902610218},
{"learn":[3.393228229],"iteration":770,"passed_time":0.6375594786,"remaining_time":0.1893659152},
{"learn":[3.389691197],"iteration":771,"passed_time":0.6381636707,"remaining_time":0.1884732085},
{"learn":[3.389626772],"iteration":772,"passed_time":0.6386934262,"remaining_time":0.1875593891},
{"learn":[3.388480222],"iteration":773,"passed_time":0.6392741316,"remaining_time":0.1866614389},
{"learn":[3.388215066],"iteration":774,"passed_time":0.639802041,"remaining_time":0.1857489796},
{"learn":[3.386324358],"iteration":775,"passed_time":0.640444901,"remaining_time":0.1848706931},
{"learn":[3.383913061],"iteration":776,"passed_time":0.6410836908,"remaining_time":0.1839918443},
{"learn":[3.382839768],"iteration":777,"passed_time":0.6417002578,"remaining_time":0.1831072715},
{"learn":[3.381961844],"iteration":778,"passed_time":0.6422645225,"remaining_time":0.1822085488},
{"learn":[3.381521703],"iteration":779,"passed_time":0.6428193639,"remaining_time":0.1813080257},
{"learn":[3.380918963],"iteration":780,"passed_time":0.6433353293,"remaining_time":0.1803974867},
{"learn":[3.377139006],"iteration":781,"passed_time":0.643914261,"remaining_time":0.1795055101},
{"learn":[3.376004372],"iteration":782,"passed_time":0.6445096759,"remaining_time":0.1786189012},
{"learn":[3.373826468],"iteration":783,"passed_time":0.6450683871,"remaining_time":0.177722923},
{"learn":[3.373546786],"iteration":784,"passed_time":0.6456748243,"remaining_time":0.1768408755},
{"learn":[3.372109181],"iteration":785,"passed_time":0.6462370824,"remaining_time":0.1759475008},
{"learn":[3.370764924],"iteration":786,"passed_time":0.6469809354,"remaining_time":0.1751041159},
{"learn":[3.367833107],"iteration":787,"passed_time":0.6476063702,"remaining_time":0.174229125},
{"learn":[3.36450404],"iteration":788,"passed_time":0.6482596514,"remaining_time":0.1733622135},
{"learn":[3.361794558],"iteration":789,"passed_time":0.6488968098,"remaining_time":0.172491557},
{"learn":[3.356880529],"iteration":790,"passed_time":0.6494991385,"remaining_time":0.1716122882},
{"learn":[3.353843509],"iteration":791,"passed_time":0.6501079101,"remaining_time":0.1707354107},
{"learn":[3.353640253],"iteration":792,"passed_time":0.6506498,"remaining_time":0.1698417511},
{"learn":[3.353055088],"iteration":793,"passed_time":0.6512216151,"remaining_time":0.1689567414},
{"learn":[3.351415617],"iteration":794,"passed_time":0.6517972205,"remaining_time":0.1680734971},
{"learn":[3.349169061],"iteration":795,"passed_time":0.6523643786,"remaining_time":0.1671888608},
{"learn":[3.346211014],"iteration":796,"passed_time":0.6529528094,"remaining_time":0.1663104395},
{"learn":[3.344560452],"iteration":797,"passed_time":0.6535190858,"remaining_time":0.165427137},
{"learn":[3.344445461],"iteration":798,"passed_time":0.6541022862,"remaining_time":0.1645488855},
{"learn":[3.342608898],"iteration":799,"passed_time":0.6546704764,"remaining_time":0.1636676191},
{"learn":[3.339572899],"iteration":800,"passed_time":0.6553340201,"remaining_time":0.162810824},
{"learn":[3.339309302],"iteration":801,"passed_time":0.6558925989,"remaining_time":0.1619285967},
{"learn":[3.33698088],"iteration":802,"passed_time":0.6565109619,"remaining_time":0.1610618425},
{"learn":[3.334746342],"iteration":803,"passed_time":0.6571071261,"remaining_time":0.1601902944},
{"learn":[3.332048511],"iteration":804,"passed_time":0.6576470596,"remaining_time":0.1593058095},
{"learn":[3.331932544],"iteration":805,"passed_time":0.6581615821,"remaining_time":0.1584160632},
{"learn":[3.330541133],"iteration":806,"passed_time":0.6587383897,"remaining_time":0.1575421428},
{"learn":[3.329124989],"iteration":807,"passed_time":0.6593931457,"remaining_time":0.1566874802},
{"learn":[3.32583918],"iteration":808,"passed_time":0.6600219655,"remaining_time":0.1558271884},
{"learn":[3.325287299],"iteration":809,"passed_time":0.6605479109,"remaining_time":0.1549433371},
{"learn":[3.322745162],"iteration":810,"passed_time":0.6612703006,"remaining_time":0.154106149},
{"learn":[3.319733662],"iteration":811,"passed_time":0.6618738117,"remaining_time":0.1532417199},
{"learn":[3.318080007],"iteration":812,"passed_time":0.6624241661,"remaining_time":0.1523657061},
{"learn":[3.317179538],"iteration":813,"passed_time":0.6630039092,"remaining_time":0.1514972077},
{"learn":[3.315685949],"iteration":814,"passed_time":0.6635578708,"remaining_time":0.1506235658},
{"learn":[3.314944576],"iteration":815,"passed_time":0.6641508809,"remaining_time":0.1497595124},
{"learn":[3.312369052],"iteration":816,"passed_time":0.6647424781,"remaining_time":0.148895806},
{"learn":[3.312321621],"iteration":817,"passed_time":0.6652173413,"remaining_time":0.1480067923},
{"learn":[3.309465776],"iteration":818,"passed_time":0.6658257343,"remaining_time":0.1471483003},
{"learn":[3.308307377],"iteration":819,"passed_time":0.6664501853,"remaining_time":0.1462939431},
{"learn":[3.308076804],"iteration":820,"passed_time":0.6670039787,"remaining_time":0.1454247408},
{"learn":[3.305643326],"iteration":821,"passed_time":0.6675840306,"remaining_time":0.144561992},
{"learn":[3.304154814],"iteration":822,"passed_time":0.6681218499,"remaining_time":0.1436908474},
{"learn":[3.303076321],"iteration":823,"passed_time":0.6687073846,"remaining_time":0.1428307035},
{"learn":[3.301746372],"iteration":824,"passed_time":0.6693192628,"remaining_time":0.1419768133},
{"learn":[3.301345455],"iteration":825,"passed_time":0.6699384754,"remaining_time":0.1411250541},
{"learn":[3.299181039],"iteration":826,"passed_time":0.6705188801,"remaining_time":0.1402657391},
{"learn":[3.297989357],"iteration":827,"passed_time":0.6711111308,"remaining_time":0.1394095586},
{"learn":[3.294775182],"iteration":828,"passed_time":0.6716911323,"remaining_time":0.1385514881},
{"learn":[3.293840636],"iteration":829,"passed_time":0.6722864973,"remaining_time":0.1376972344},
{"learn":[3.289279397],"iteration":830,"passed_time":0.6729614193,"remaining_time":0.1368597832},
{"learn":[3.286204979],"iteration":831,"passed_time":0.6735990492,"remaining_time":0.1360151926},
{"learn":[3.284833593],"iteration":832,"passed_time":0.674162239,"remaining_time":0.1351561752},
{"learn":[3.283519914],"iteration":833,"passed_time":0.6747446481,"remaining_time":0.1343016925},
{"learn":[3.282853026],"iteration":834,"passed_time":0.6753890309,"remaining_time":0.1334601079},
{"learn":[3.281944673],"iteration":835,"passed_time":0.6759334136,"remaining_time":0.1325993778},
{"learn":[3.279764865],"iteration":836,"passed_time":0.6764564833,"remaining_time":0.131735253},
{"learn":[3.277468839],"iteration":837,"passed_time":0.6770834014,"remaining_time":0.1308920179},
{"learn":[3.277124974],"iteration":838,"passed_time":0.6777203192,"remaining_time":0.1300512174},
{"learn":[3.275636037],"iteration":839,"passed_time":0.678291077,"remaining_time":0.1291983004},
{"learn":[3.274413635],"iteration":840,"passed_time":0.6788474811,"remaining_time":0.1283433407},
{"learn":[3.272636087],"iteration":841,"passed_time":0.6794164632,"remaining_time":0.1274914503},
{"learn":[3.269644466],"iteration":842,"passed_time":0.6800126393,"remaining_time":0.1266452958},
{"learn":[3.26852083],"iteration":843,"passed_time":0.6805533143,"remaining_time":0.1257894752},
{"learn":[3.267820927],"iteration":844,"passed_time":0.6811085889,"remaining_time":0.1249370784},
{"learn":[3.267331099],"iteration":845,"passed_time":0.6816660874,"remaining_time":0.124085789},
{"learn":[3.267231014],"iteration":846,"passed_time":0.6822134057,"remaining_time":0.1232333543},
{"learn":[3.267158695],"iteration":847,"passed_time":0.6827440406,"remaining_time":0.1223786488},
{"learn":[3.264718705],"iteration":848,"passed_time":0.6832914694,"remaining_time":0.1215276936},
{"learn":[3.261678512],"iteration":849,"passed_time":0.6839285375,"remaining_time":0.1206932713},
{"learn":[3.261368381],"iteration":850,"passed_time":0.684471768,"remaining_time":0.119842883},
{"learn":[3.260128799],"iteration":851,"passed_time":0.6850060999,"remaining_time":0.1189916699},
{"learn":[3.258972952],"iteration":852,"passed_time":0.6855609157,"remaining_time":0.1181447299},
{"learn":[3.258724846],"iteration":853,"passed_time":0.6861031915,"remaining_time":0.1172963302},
{"learn":[3.25686724],"iteration":854,"passed_time":0.6866360007,"remaining_time":0.1164470411},
{"learn":[3.255750259],"iteration":855,"passed_time":0.687225947,"remaining_time":0.1156081032},
{"learn":[3.254915866],"iteration":856,"passed_time":0.6877675317,"remaining_time":0.1147616768},
{"learn":[3.254348625],"iteration":857,"passed_time":0.6883074252,"remaining_time":0.1139156811},
{"learn":[3.253408514],"iteration":858,"passed_time":0.6888546731,"remaining_time":0.1130716052},
{"learn":[3.253291714],"iteration":859,"passed_time":0.6895039363,"remaining_time":0.1122448268},
{"learn":[3.250186342],"iteration":860,"passed_time":0.6901367859,"remaining_time":0.111415811},
{"learn":[3.249141318],"iteration":861,"passed_time":0.6906724409,"remaining_time":0.1105716901},
{"learn":[3.246300388],"iteration":862,"passed_time":0.6912281861,"remaining_time":0.1097314733},
{"learn":[3.245205135],"iteration":863,"passed_time":0.6918528299,"remaining_time":0.1089027603},
{"learn":[3.244403535],"iteration":864,"passed_time":0.6925112612,"remaining_time":0.1080797922},
{"learn":[3.244211781],"iteration":865,"passed_time":0.6930836298,"remaining_time":0.1072438873},
{"learn":[3.242286347],"iteration":866,"passed_time":0.6936150262,"remaining_time":0.1064023051},
{"learn":[3.239606746],"iteration":867,"passed_time":0.6941516731,"remaining_time":0.105562236},
{"learn":[3.236773361],"iteration":868,"passed_time":0.694725024,"remaining_time":0.1047283983},
{"learn":[3.234552446],"iteration":869,"passed_time":0.6952535145,"remaining_time":0.1038884562},
{"learn":[3.233724647],"iteration":870,"passed_time":0.6957937386,"remaining_time":0.103050967},
{"learn":[3.230851485],"iteration":871,"passed_time":0.6963951076,"remaining_time":0.1022231351},
{"learn":[3.227728941],"iteration":872,"passed_time":0.6970347612,"remaining_time":0.1014013914},
{"learn":[3.225787575],"iteration":873,"passed_time":0.6975838209,"remaining_time":0.1005670039},
{"learn":[3.222797487],"iteration":874,"passed_time":0.6981851576,"remaining_time":0.0997407368},
{"learn":[3.22137014],"iteration":875,"passed_time":0.6987474982,"remaining_time":0.09890946322},
{"learn":[3.219701963],"iteration":876,"passed_time":0.6993012473,"remaining_time":0.09807759797},
{"learn":[3.21783327],"iteration":877,"passed_time":0.6999357102,"remaining_time":0.0972575816},
{"learn":[3.217713355],"iteration":878,"passed_time":0.7004674977,"remaining_time":0.0964238535},
{"learn":[3.217666091],"iteration":879,"passed_time":0.7010230125,"remaining_time":0.09559404716},
{"learn":[3.214962005],"iteration":880,"passed_time":0.7016487382,"remaining_time":0.09477434715},
{"learn":[3.214081828],"iteration":881,"passed_time":0.7022002249,"remaining_time":0.0939451548},
{"learn":[3.213358337],"iteration":882,"passed_time":0.7027714934,"remaining_time":0.0931192126},
{"learn":[3.210850401],"iteration":883,"passed_time":0.7034189202,"remaining_time":0.0923038402},
{"learn":[3.207810328],"iteration":884,"passed_time":0.704102116,"remaining_time":0.0914934953},
{"learn":[3.204935073],"iteration":885,"passed_time":0.704724951,"remaining_time":0.0906756709},
{"learn":[3.20280198],"iteration":886,"passed_time":0.7054155269,"remaining_time":0.08986691605},
{"learn":[3.200663495],"iteration":887,"passed_time":0.7060890305,"remaining_time":0.08905627412},
{"learn":[3.197301669],"iteration":888,"passed_time":0.7067328805,"remaining_time":0.08824223817},
{"learn":[3.195666943],"iteration":889,"passed_time":0.7074095383,"remaining_time":0.08743263957},
{"learn":[3.193886506],"iteration":890,"passed_time":0.7080815745,"remaining_time":0.08662277399},
{"learn":[3.190601248],"iteration":891,"passed_time":0.7086380011,"remaining_time":0.08579921987},
{"learn":[3.188983797],"iteration":892,"passed_time":0.7091799787,"remaining_time":0.08497453273},
{"learn":[3.187365749],"iteration":893,"passed_time":0.7097587605,"remaining_time":0.08415484185},
{"learn":[3.186160771],"iteration":894,"passed_time":0.7102880928,"remaining_time":0.08332988798},
{"learn":[3.185358981],"iteration":895,"passed_time":0.7108050702,"remaining_time":0.08250415993},
{"learn":[3.183832164],"iteration":896,"passed_time":0.711337679,"remaining_time":0.0816809152},
{"learn":[3.183106966],"iteration":897,"passed_time":0.711870859,"remaining_time":0.08085838264},
{"learn":[3.182838152],"iteration":898,"passed_time":0.7124239088,"remaining_time":0.08003872613},
{"learn":[3.180835453],"iteration":899,"passed_time":0.7129623794,"remaining_time":0.07921804215},
{"learn":[3.179957348],"iteration":900,"passed_time":0.7134774129,"remaining_time":0.07839540941},
{"learn":[3.179752966],"iteration":901,"passed_time":0.7140035187,"remaining_time":0.07757466168},
{"learn":[3.178851983],"iteration":902,"passed_time":0.7145471897,"remaining_time":0.07675645338},
{"learn":[3.176748586],"iteration":903,"passed_time":0.7150741371,"remaining_time":0.07593707651},
{"learn":[3.172960988],"iteration":904,"passed_time":0.7156212651,"remaining_time":0.07512046429},
{"learn":[3.172794225],"iteration":905,"passed_time":0.7161621605,"remaining_time":0.07430380032},
{"learn":[3.169996507],"iteration":906,"passed_time":0.7167332466,"remaining_time":0.07349084006},
{"learn":[3.16813015],"iteration":907,"passed_time":0.7175172799,"remaining_time":0.07269998871},
{"learn":[3.166920871],"iteration":908,"passed_time":0.7181450998,"remaining_time":0.07189351384},
{"learn":[3.16531606],"iteration":909,"passed_time":0.7187927993,"remaining_time":0.07108939773},
{"learn":[3.162035247],"iteration":910,"passed_time":0.7194186355,"remaining_time":0.07028348909},
{"learn":[3.16189467],"iteration":911,"passed_time":0.7199890623,"remaining_time":0.06947262882},
{"learn":[3.161008416],"iteration":912,"passed_time":0.7206382129,"remaining_time":0.06866979684},
{"learn":[3.160560787],"iteration":913,"passed_time":0.7213653721,"remaining_time":0.06787464114},
{"learn":[3.160416261],"iteration":914,"passed_time":0.7219591558,"remaining_time":0.06706724398},
{"learn":[3.15844291],"iteration":915,"passed_time":0.7225106224,"remaining_time":0.06625643262},
{"learn":[3.155040501],"iteration":916,"passed_time":0.7231000328,"remaining_time":0.06544962129},
{"learn":[3.154937548],"iteration":917,"passed_time":0.7236685239,"remaining_time":0.06464141499},
{"learn":[3.153721161],"iteration":918,"passed_time":0.7242119666,"remaining_time":0.06383152263},
{"learn":[3.153170511],"iteration":919,"passed_time":0.7248280207,"remaining_time":0.06302852354},
{"learn":[3.153113601],"iteration":920,"passed_time":0.7253584373,"remaining_time":0.06221858474},
{"learn":[3.150607379],"iteration":921,"passed_time":0.7259365049,"remaining_time":0.06141328349},
{"learn":[3.148408359],"iteration":922,"passed_time":0.7264956773,"remaining_time":0.06060689832},
{"learn":[3.147495728],"iteration":923,"passed_time":0.7270623141,"remaining_time":0.0598016622},
{"learn":[3.146946235],"iteration":924,"passed_time":0.7276167771,"remaining_time":0.0589959549},
{"learn":[3.14472738],"iteration":925,"passed_time":0.7281623316,"remaining_time":0.05819007833},
{"learn":[3.144469477],"iteration":926,"passed_time":0.7286998803,"remaining_time":0.05738413297},
{"learn":[3.142975516],"iteration":927,"passed_time":0.7292678804,"remaining_time":0.05658112865},
{"learn":[3.14079113],"iteration":928,"passed_time":0.7298358223,"remaining_time":0.05577862581},
{"learn":[3.138173032],"iteration":929,"passed_time":0.7303952024,"remaining_time":0.05497598298},
{"learn":[3.136352813],"iteration":930,"passed_time":0.7310348663,"remaining_time":0.05417981286},
{"learn":[3.133735004],"iteration":931,"passed_time":0.7315512326,"remaining_time":0.05337498263},
{"learn":[3.1319496],"iteration":932,"passed_time":0.7321219378,"remaining_time":0.05257467292},
{"learn":[3.129865343],"iteration":933,"passed_time":0.7326966733,"remaining_time":0.05177513965},
{"learn":[3.129830206],"iteration":934,"passed_time":0.7331207719,"remaining_time":0.05096561516},
{"learn":[3.126676562],"iteration":935,"passed_time":0.7336653548,"remaining_time":0.05016515246},
{"learn":[3.12645665],"iteration":936,"passed_time":0.7341926453,"remaining_time":0.04936407327},
{"learn":[3.126378007],"iteration":937,"passed_time":0.7348064771,"remaining_time":0.04856929806},
{"learn":[3.124621914],"iteration":938,"passed_time":0.7354130122,"remaining_time":0.04777443423},
{"learn":[3.123379018],"iteration":939,"passed_time":0.7359818658,"remaining_time":0.0469775659},
{"learn":[3.123332451],"iteration":940,"passed_time":0.7365240114,"remaining_time":0.04617950762},
{"learn":[3.122432444],"iteration":941,"passed_time":0.7371234768,"remaining_time":0.04538552192},
{"learn":[3.121889006],"iteration":942,"passed_time":0.7376851314,"remaining_time":0.0445896633},
{"learn":[3.121070914],"iteration":943,"passed_time":0.7382209069,"remaining_time":0.04379276566},
{"learn":[3.118444705],"iteration":944,"passed_time":0.7387444876,"remaining_time":0.04299571092},
{"learn":[3.116820458],"iteration":945,"passed_time":0.7393554837,"remaining_time":0.04220422423},
{"learn":[3.114971041],"iteration":946,"passed_time":0.739921229,"remaining_time":0.04141058621},
{"learn":[3.114685138],"iteration":947,"passed_time":0.740543778,"remaining_time":0.04062054479},
{"learn":[3.113399363],"iteration":948,"passed_time":0.7410693026,"remaining_time":0.03982564219},
{"learn":[3.110575399],"iteration":949,"passed_time":0.7415902581,"remaining_time":0.03903106621},
{"learn":[3.110466553],"iteration":950,"passed_time":0.7421463164,"remaining_time":0.03823887434},
{"learn":[3.108691641],"iteration":951,"passed_time":0.7427003861,"remaining_time":0.03744707829},
{"learn":[3.107898017],"iteration":952,"passed_time":0.7432303296,"remaining_time":0.03665459128},
{"learn":[3.105551729],"iteration":953,"passed_time":0.7437735597,"remaining_time":0.03586329533},
{"learn":[3.104824945],"iteration":954,"passed_time":0.7443222229,"remaining_time":0.0350727749},
{"learn":[3.103186704],"iteration":955,"passed_time":0.7451341601,"remaining_time":0.03429487766},
{"learn":[3.102330655],"iteration":956,"passed_time":0.7458288742,"remaining_time":0.03351164221},
{"learn":[3.102291298],"iteration":957,"passed_time":0.7465620276,"remaining_time":0.03273027678},
{"learn":[3.100363529],"iteration":958,"passed_time":0.7472204367,"remaining_time":0.03194581638},
{"learn":[3.097871596],"iteration":959,"passed_time":0.7478442285,"remaining_time":0.03116017619},
{"learn":[3.097372213],"iteration":960,"passed_time":0.748438471,"remaining_time":0.03037367364},
{"learn":[3.095981813],"iteration":961,"passed_time":0.7490338355,"remaining_time":0.02958761512},
{"learn":[3.095347452],"iteration":962,"passed_time":0.749683181,"remaining_time":0.02880402668},
{"learn":[3.094728409],"iteration":963,"passed_time":0.75026196,"remaining_time":0.02801808149},
{"learn":[3.094118537],"iteration":964,"passed_time":0.7508486577,"remaining_time":0.02723285287},
{"learn":[3.093793695],"iteration":965,"passed_time":0.7513686511,"remaining_time":0.02644568751},
{"learn":[3.092581602],"iteration":966,"passed_time":0.7518838751,"remaining_time":0.02565891197},
{"learn":[3.091694202],"iteration":967,"passed_time":0.7525006829,"remaining_time":0.02487605563},
{"learn":[3.090298312],"iteration":968,"passed_time":0.753070346,"remaining_time":0.02409203377},
{"learn":[3.090020107],"iteration":969,"passed_time":0.7536035661,"remaining_time":0.02330732679},
{"learn":[3.088949869],"iteration":970,"passed_time":0.754181518,"remaining_time":0.02252447376},
{"learn":[3.086700204],"iteration":971,"passed_time":0.7547952095,"remaining_time":0.02174307188},
{"learn":[3.086584317],"iteration":972,"passed_time":0.755337137,"remaining_time":0.02096002333},
{"learn":[3.084850742],"iteration":973,"passed_time":0.7558734934,"remaining_time":0.02017732118},
{"learn":[3.084239948],"iteration":974,"passed_time":0.7564184047,"remaining_time":0.01939534371},
{"learn":[3.082561673],"iteration":975,"passed_time":0.7569898715,"remaining_time":0.01861450504},
{"learn":[3.07991814],"iteration":976,"passed_time":0.7575290836,"remaining_time":0.01783333564},
{"learn":[3.079350277],"iteration":977,"passed_time":0.758058025,"remaining_time":0.01705243001},
{"learn":[3.077637462],"iteration":978,"passed_time":0.7585691708,"remaining_time":0.01627165739},
{"learn":[3.076733301],"iteration":979,"passed_time":0.759170237,"remaining_time":0.01549327014},
{"learn":[3.07594065],"iteration":980,"passed_time":0.7597982093,"remaining_time":0.01471576552},
{"learn":[3.072594655],"iteration":981,"passed_time":0.7603054873,"remaining_time":0.01393635313},
{"learn":[3.071977674],"iteration":982,"passed_time":0.7608851484,"remaining_time":0.01315874621},
{"learn":[3.069532634],"iteration":983,"passed_time":0.761457016,"remaining_time":0.01238141489},
{"learn":[3.068870784],"iteration":984,"passed_time":0.7619725405,"remaining_time":0.01160364275},
{"learn":[3.068801463],"iteration":985,"passed_time":0.7625575845,"remaining_time":0.01082738964},
{"learn":[3.067433249],"iteration":986,"passed_time":0.7631126484,"remaining_time":0.01005112911},
{"learn":[3.065611456],"iteration":987,"passed_time":0.7636354375,"remaining_time":0.009274924342},
{"learn":[3.063039162],"iteration":988,"passed_time":0.7642237402,"remaining_time":0.00849996071},
{"learn":[3.06177873],"iteration":989,"passed_time":0.7648335017,"remaining_time":0.007725590927},
{"learn":[3.061689148],"iteration":990,"passed_time":0.7653679542,"remaining_time":0.006950869413},
{"learn":[3.058984039],"iteration":991,"passed_time":0.7659523767,"remaining_time":0.006177035296},
{"learn":[3.057492984],"iteration":992,"passed_time":0.7665101564,"remaining_time":0.005403394859},
{"learn":[3.057290731],"iteration":993,"passed_time":0.7670542582,"remaining_time":0.004630106187},
{"learn":[3.056068348],"iteration":994,"passed_time":0.76756841,"remaining_time":0.003857127688},
{"learn":[3.054987307],"iteration":995,"passed_time":0.7681058686,"remaining_time":0.003084762524},
{"learn":[3.054200234],"iteration":996,"passed_time":0.7686466334,"remaining_time":0.002312878536},
{"learn":[3.052732869],"iteration":997,"passed_time":0.7692797263,"remaining_time":0.001541642738},
{"learn":[3.051787862],"iteration":998,"passed_time":0.7698593974,"remaining_time":0.0007706300275},
{"learn":[3.051366222],"iteration":999,"passed_time":0.7703878579,"remaining_time":0}
]}